[
  {
    "INDEKS": "49685",
    "NAZWA": "LEKORNA WAFLE TORTOWE RAINBOW 90G UKRAINA",
    "RANKING": "1",
    "Grupa": "POZOSTAŁE UKRAINA",
    "Producent": "LEKORNA",
    "Kod Ean": "4820143330026",
    "x": "LEKORNA WAFLE TORTOWE RAINBOW 90G UKRAINA"
  },
  {
    "INDEKS": "53237",
    "NAZWA": "ROSHEN WAFLE 72G Z NADZIENIEM KAKAOWYM UKRAINA",
    "RANKING": "2",
    "Grupa": "SŁODYCZE UKRAINA",
    "Producent": "ROSHEN",
    "Kod Ean": "4823077641329",
    "x": "WAFLE ROSHEN 72G Z NADZIENIEM KAKAOWYM UKRAINA"
  },
  {
    "INDEKS": "53257",
    "NAZWA": "ROSHEN WAFELKI 216G Z NADZIENIEM KAKAOWYM UKRAINA",
    "RANKING": "3",
    "Grupa": "SŁODYCZE UKRAINA",
    "Producent": "ROSHEN",
    "Kod Ean": "4823077641312",
    "x": "WAFELKI ROSHEN 216G Z NADZIENIEM KAKAOWYM UKRAINA"
  },
  {
    "INDEKS": "53259",
    "NAZWA": "ROSHEN WAFELKI 216G Z NADZIENIEM ORZECH LASKOWY UKRAINA",
    "RANKING": "4",
    "Grupa": "SŁODYCZE UKRAINA",
    "Producent": "ROSHEN",
    "Kod Ean": "4823077625626",
    "x": "WAFELKI ROSHEN 216G Z NADZIENIEM ORZECH LASKOWY UKRAINA"
  },
  {
    "INDEKS": "53256",
    "NAZWA": "ROSHEN WAFELKI 216G Z NADZIENIEM MLECZNYM UKRAINA",
    "RANKING": "5",
    "Grupa": "SŁODYCZE UKRAINA",
    "Producent": "ROSHEN",
    "Kod Ean": "4823077625589",
    "x": "WAFELKI ROSHEN 216G Z NADZIENIEM MLECZNYM UKRAINA"
  },
  {
    "INDEKS": "40291",
    "NAZWA": "ROSHEN WAFLE 72G Z NADZIENIEM ORZECHOWYM UKRAINA",
    "RANKING": "6",
    "Grupa": "SŁODYCZE UKRAINA",
    "Producent": "ROSHEN",
    "Kod Ean": "4823077621659",
    "x": "ROSHEN WAFLE 72G Z NADZIENIEM ORZECHOWYM UKRAINA"
  },
  {
    "INDEKS": "57714",
    "NAZWA": "ROSHEN HERBATNIKI 185G O SMAKU MLEKA SKONDENSOWANEGO UKRAINA",
    "RANKING": "7",
    "Grupa": "SŁODYCZE UKRAINA",
    "Producent": "ROSHEN",
    "Kod Ean": "4823077614675",
    "x": "HERBATNIKI ROSHEN 185G O SMAKU MLEKA SKONDENSOWANEGO UKRAINA"
  },
  {
    "INDEKS": "53264",
    "NAZWA": "ROSHEN WAFELKI 216G Z NADZIENIEM KOKOSOWO MIGDALOWYM UKRAINA",
    "RANKING": "8",
    "Grupa": "SŁODYCZE UKRAINA",
    "Producent": "ROSHEN",
    "Kod Ean": "4823077640988",
    "x": "WAFERS ROSHEN 216G COCONUT AND ALMONDS UKRAINE"
  },
  {
    "INDEKS": "45329",
    "NAZWA": "FLINT SUCHARKI 70G O SMAKU KIELBAS BAWARSKICH UKRAINA",
    "RANKING": "9",
    "Grupa": "PRZEKĄSKI UKRAINA",
    "Producent": "FLINT",
    "Kod Ean": "4820182743139",
    "x": "SUCHARKI FLINT 70G O SMAKU KIELBAS BAWARSKICH UKRAINA"
  },
  {
    "INDEKS": "53263",
    "NAZWA": "ROSHEN WAFELKI 216G Z NADZIENIEM KAKAOWO MLECZNYM UKRAINA",
    "RANKING": "10",
    "Grupa": "SŁODYCZE UKRAINA",
    "Producent": "ROSHEN",
    "Kod Ean": "4823077632112",
    "x": "WAFELKI ROSHEN 216G Z NADZIENIEM KAKAOWO MLECZNYM UKRAINA"
  },
  {
    "INDEKS": "40290",
    "NAZWA": "ROSHEN WAFLE 72G Z NADZIENIEM MLECZNYM UKRAINA",
    "RANKING": "11",
    "Grupa": "SŁODYCZE UKRAINA",
    "Producent": "ROSHEN",
    "Kod Ean": "4823077621635",
    "x": "WAFLE ROSHEN 72G Z NADZIENIEM MLECZNYM UKRAINA"
  },
  {
    "INDEKS": "45968",
    "NAZWA": "LEKORNA WAFLE TORTOWE DUET Z DODATKIEM KAKAO 90G UKRAINA",
    "RANKING": "12",
    "Grupa": "POZOSTAŁE UKRAINA",
    "Producent": "LEKORNA",
    "Kod Ean": "4820143330989",
    "x": "LEKORNA WAFLE TORTOWE DUET Z DODATKIEM KAKAO 90G UKRAINA"
  },
  {
    "INDEKS": "53260",
    "NAZWA": "ROSHEN WAFELKI 216G Z NADZIENIEM LEMON CREAM UKRAINA",
    "RANKING": "13",
    "Grupa": "SŁODYCZE UKRAINA",
    "Producent": "ROSHEN",
    "Kod Ean": "4823077636172",
    "x": "WAFELKI ROSHEN 216G Z NADZIENIEM LEMON CREAM UKRAINA"
  },
  {
    "INDEKS": "45963",
    "NAZWA": "LEKORNA WAFLE TORTOWE 90G UKRAINA",
    "RANKING": "14",
    "Grupa": "POZOSTAŁE UKRAINA",
    "Producent": "LEKORNA",
    "Kod Ean": "4820143330019",
    "x": "LEKORNA WAFLE TORTOWE 90G UKRAINA"
  },
  {
    "INDEKS": "53253",
    "NAZWA": "ROSHEN WAFLE 72G Z NADZIENIEM CYTRYNOWYM UKRAINA",
    "RANKING": "15",
    "Grupa": "SŁODYCZE UKRAINA",
    "Producent": "ROSHEN",
    "Kod Ean": "4823077642401",
    "x": "WAFLE ROSHEN 72G Z NADZIENIEM CYTRYNOWYM UKRAINA"
  },
  {
    "INDEKS": "55694",
    "NAZWA": "LUKS CHIPSY ZIEMNIACZANE O SMAKU BEKONU 125G UKRAINA",
    "RANKING": "16",
    "Grupa": "PRZEKĄSKI UKRAINA",
    "Producent": "LUKS",
    "Kod Ean": "7622202224409",
    "x": "LUKS CHIPSY ZIEMNIACZANE O SMAKU BEKONU 125G UKRAINA"
  },
  {
    "INDEKS": "55695",
    "NAZWA": "LUKS CHIPSY ZIEMNIACZANE O SMAKU SERA 125G UKRAINA",
    "RANKING": "17",
    "Grupa": "PRZEKĄSKI UKRAINA",
    "Producent": "LUKS",
    "Kod Ean": "7622202224379",
    "x": "LUKS CHIPSY ZIEMNIACZANE O SMAKU SERA 125G UKRAINA"
  },
  {
    "INDEKS": "45324",
    "NAZWA": "FLINT SUCHARKI 70G O SMAKU SZASZLYKA UKRAINA",
    "RANKING": "18",
    "Grupa": "PRZEKĄSKI UKRAINA",
    "Producent": "FLINT",
    "Kod Ean": "4820182743016",
    "x": "SUCHARKI FLINT 70G O SMAKU SZASZLYKA UKRAINA"
  },
  {
    "INDEKS": "57684",
    "NAZWA": "SZCZEDRO MAJONEZ 300G 72% TLUSZCZU PREMIUM UKRAINA",
    "RANKING": "19",
    "Grupa": "DODATKI DO POTRAW UKRAINA",
    "Producent": "SZCZEDRO",
    "Kod Ean": "4823097407196",
    "x": "MAJONEZ SZCZEDRO 300G 72% TLUSZCZU PREMIUM UKRAINA"
  },
  {
    "INDEKS": "54904",
    "NAZWA": "ZHITNIZA KASZA GRYCZANA 800G UKRAINA",
    "RANKING": "20",
    "Grupa": "PRODUKTY PODSTAWOWE UKRAINA",
    "Producent": "ZHITNIZA",
    "Kod Ean": "4030957561305",
    "x": "KASZA GRYCZANA 800G UKRAINA ZHITNIZA"
  },
  {
    "INDEKS": "57680",
    "NAZWA": "SZCZEDRO MAJONEZ 300G 80% TLUSZCZU LWOWSKI UKRAINA",
    "RANKING": "21",
    "Grupa": "DODATKI DO POTRAW UKRAINA",
    "Producent": "SCHEDRO",
    "Kod Ean": "4823097407288",
    "x": "MAJONEZ SZCZEDRO 300G 80% TLUSZCZU LWOWSKI UKRAINA"
  },
  {
    "INDEKS": "57875",
    "NAZWA": "ROSHEN BATON 33G CZEKOLADOWY UKRAINA",
    "RANKING": "22",
    "Grupa": "SŁODYCZE UKRAINA",
    "Producent": "ROSHEN",
    "Kod Ean": "4823077636837",
    "x": "BATON ROSHEN 33G CZEKOLADOWY UKRAINA"
  },
  {
    "INDEKS": "57721",
    "NAZWA": "ROSHEN HERBATNIKI 185G O SMAKU WANILIOWYM UKRAINA",
    "RANKING": "23",
    "Grupa": "SŁODYCZE UKRAINA",
    "Producent": "ROSHEN",
    "Kod Ean": "4823077614699",
    "x": "HERBATNIKI ROSHEN 185G O SMAKU WANILIOWYM UKRAINA"
  },
  {
    "INDEKS": "55696",
    "NAZWA": "LUKS CHIPSY ZIEMNIACZANE O SMAKU PAPRYKI 125G UKRAINA",
    "RANKING": "24",
    "Grupa": "PRZEKĄSKI UKRAINA",
    "Producent": "LUKS",
    "Kod Ean": "7622202224430",
    "x": "LUKS CHIPSY ZIEMNIACZANE O SMAKU PAPRYKI 125G UKRAINA"
  },
  {
    "INDEKS": "56232",
    "NAZWA": "RODYNA ZEFIR BIALO ROZOWY 400G UKRAINA",
    "RANKING": "25",
    "Grupa": "SŁODYCZE UKRAINA",
    "Producent": "RODYNA",
    "Kod Ean": "4820024388160",
    "x": "RODYNA ZEFIR BIALO ROZOWY 400G UKRAINA"
  },
  {
    "INDEKS": "59672",
    "NAZWA": "YAW SUCHARKI 50G BEKON UKRAINA",
    "RANKING": "27",
    "Grupa": "PRZEKĄSKI UKRAINA",
    "Producent": "YAW!",
    "Kod Ean": "4841900001515",
    "x": "SUCHARKI YAW 50G BEKON UKRAINA"
  },
  {
    "INDEKS": "54277",
    "NAZWA": "DOBRIM LUDJAM CHRUPIACE BAJGLE MINI O SMAKU WANILIOWYM 500G UKRAINA",
    "RANKING": "28",
    "Grupa": "SŁODYCZE UKRAINA",
    "Producent": "DOBRIM LUDJAM",
    "Kod Ean": "4823117506144",
    "x": "DOBRIM LUDJAM CHRUPIACE BAJGLE MINI O SMAKU WANILIOWYM 500G UKRAINA"
  },
  {
    "INDEKS": "53017",
    "NAZWA": "SALTOWSKI KIELBASA 320G KIJOWSKA UKRAINA",
    "RANKING": "29",
    "Grupa": "MIĘSO I WĘDLINY UKRAINA",
    "Producent": "SALTOWSKI",
    "Kod Ean": "5906747117795",
    "x": "KIELBASA SALTOWSKI 320G KIJOWSKA UKRAINA"
  },
  {
    "INDEKS": "56778",
    "NAZWA": "OLIS MUSZTARDA 140G STRONG UKRAINA",
    "RANKING": "30",
    "Grupa": "DODATKI DO POTRAW UKRAINA",
    "Producent": "OLIS",
    "Kod Ean": "4820015713872",
    "x": "MUSZTARDA OLIS 140G STRONG UKRAINA"
  },
  {
    "INDEKS": "56230",
    "NAZWA": "RODYNA ZEFIR O SMAKU WANILINOWYM 400G UKRAINA",
    "RANKING": "31",
    "Grupa": "SŁODYCZE UKRAINA",
    "Producent": "RODYNA",
    "Kod Ean": "4820024388153",
    "x": "RODYNA ZEFIR O SMAKU WANILINOWYM 400G UKRAINA"
  },
  {
    "INDEKS": "45323",
    "NAZWA": "FLINT SUCHARKI 70G O SMAKU CZERWONEGO KAWIORU UKRAINA",
    "RANKING": "32",
    "Grupa": "PRZEKĄSKI UKRAINA",
    "Producent": "FLINT",
    "Kod Ean": "4820182742941",
    "x": "SUCHARKI FLINT 70G O SMAKU CZERWONEGO KAWIORU UKRAINA"
  },
  {
    "INDEKS": "45327",
    "NAZWA": "FLINT SUCHARKI 70G O SMAKU KRABA UKRAINA",
    "RANKING": "33",
    "Grupa": "PRZEKĄSKI UKRAINA",
    "Producent": "FLINT",
    "Kod Ean": "4820182742866",
    "x": "SUCHARKI FLINT 70G O SMAKU KRABA UKRAINA"
  },
  {
    "INDEKS": "53012",
    "NAZWA": "SALTOWSKI KIELBASA 700G DOKTORSKA UKRAINA",
    "RANKING": "34",
    "Grupa": "MIĘSO I WĘDLINY UKRAINA",
    "Producent": "SALTOWSKI",
    "Kod Ean": "5906747117856",
    "x": "KIELBASA SALTOWSKI 700G DOKTORSKA UKRAINA"
  },
  {
    "INDEKS": "59670",
    "NAZWA": "YAW SUCHARKI 50G POMIDORY Z ZIOLAMI UKRAINA",
    "RANKING": "35",
    "Grupa": "PRZEKĄSKI UKRAINA",
    "Producent": "YAW!",
    "Kod Ean": "4841900001058",
    "x": "SUCHARKI YAW 50G POMIDORY Z ZIOLAMI UKRAINA"
  },
  {
    "INDEKS": "54825",
    "NAZWA": "STEINHAUER MLEKO SKONDENSOWANE SLODZONE 397G UKRAINA",
    "RANKING": "36",
    "Grupa": "PUSZKI I SŁOIKI UKRAINA",
    "Producent": "STEINHAUER",
    "Kod Ean": "4030011300116",
    "x": "STEINHAUER MLEKO SKONDENSOWANE SLODZONE 397G UKRAINA"
  },
  {
    "INDEKS": "54844",
    "NAZWA": "SZCZEDRO MAJONEZ 300G 30% TLUSZCZU SALATKOWY UKRAINA",
    "RANKING": "37",
    "Grupa": "DODATKI DO POTRAW UKRAINA",
    "Producent": "SZEDRO",
    "Kod Ean": "4823097407134",
    "x": "MAJONEZ SZCZEDRO 300G 30% TLUSZCZU SALATKOWY UKRAINA"
  },
  {
    "INDEKS": "59671",
    "NAZWA": "YAW SUCHARKI 50G SER UKRAINA",
    "RANKING": "39",
    "Grupa": "PRZEKĄSKI UKRAINA",
    "Producent": "YAW!",
    "Kod Ean": "4841900000860",
    "x": "SUCHARKI YAW 50G SER UKRAINA"
  },
  {
    "INDEKS": "59677",
    "NAZWA": "YAW SUCHARKI 120G SMIETANA Z CEBULKA UKRAINA",
    "RANKING": "40",
    "Grupa": "PRZEKĄSKI UKRAINA",
    "Producent": "YAW!",
    "Kod Ean": "4841900001829",
    "x": "SUCHARKI YAW 120G SMIETANA Z CEBULKA UKRAINA"
  },
  {
    "INDEKS": "57865",
    "NAZWA": "ROSHEN CIASTKA 180G MULTICAKE Z KREMEM KAKAOWYM UKRAINA",
    "RANKING": "41",
    "Grupa": "SŁODYCZE UKRAINA",
    "Producent": "ROSHEN",
    "Kod Ean": "4823077609077",
    "x": "CIASTKA ROSHEN 180G MULTICAKE Z KREMEM KAKAOWYM UKRAINA"
  },
  {
    "INDEKS": "53034",
    "NAZWA": "SALTOWSKI KIELBASA 350G SUMSKA UKRAINA",
    "RANKING": "43",
    "Grupa": "MIĘSO I WĘDLINY UKRAINA",
    "Producent": "SALTOWSKI",
    "Kod Ean": "5906747117832",
    "x": "KIELBASA SALTOWSKI 350G SUMSKA UKRAINA"
  },
  {
    "INDEKS": "59678",
    "NAZWA": "YAW SUCHARKI 120G SER UKRAINA",
    "RANKING": "44",
    "Grupa": "PRZEKĄSKI UKRAINA",
    "Producent": "YAW!",
    "Kod Ean": "4841900001799",
    "x": "SUCHARKI YAW 120G SER UKRAINA"
  },
  {
    "INDEKS": "59680",
    "NAZWA": "YAW SUCHARKI 120G BEKON UKRAINA",
    "RANKING": "45",
    "Grupa": "PRZEKĄSKI UKRAINA",
    "Producent": "YAW!",
    "Kod Ean": "4841900001843",
    "x": "SUCHARKI YAW 120G BEKON UKRAINA"
  },
  {
    "INDEKS": "56776",
    "NAZWA": "OLIS SOS MAJONEZOWY EXTRA 300G UKRAINA",
    "RANKING": "46",
    "Grupa": "DODATKI DO POTRAW UKRAINA",
    "Producent": "OLIS",
    "Kod Ean": "4820015714794",
    "x": "OLIS SOS MAJONEZOWY EXTRA 300G UKRAINA"
  },
  {
    "INDEKS": "46380",
    "NAZWA": "SLADOSVIT MLEKO SKONDENSOWANE 500G IRYSKA IMPERIAL PLUS UKRAINA",
    "RANKING": "47",
    "Grupa": "PUSZKI I SŁOIKI CHŁODZONE UKRAINA",
    "Producent": "SLADOSVIT",
    "Kod Ean": "4820034600818",
    "x": "MLEKO SKONDENSOWANE SLADOSVIT 500G IRYSKA IMPERIAL PLUS UKRAINA"
  },
  {
    "INDEKS": "48258",
    "NAZWA": "AVK 200G BAMBUK Z MLEKIEM SKONDESOWANYM UKRAINA",
    "RANKING": "48",
    "Grupa": "SŁODYCZE UKRAINA",
    "Producent": "AVK",
    "Kod Ean": "4823105813476",
    "x": "AVK 200G BAMBUK Z MLEKIEM SKONDESOWANYM UKRAINA"
  },
  {
    "INDEKS": "53031",
    "NAZWA": "SALTOWSKI KIELBASA 300G SERWELAT UKRAINSKI UKRAINA",
    "RANKING": "49",
    "Grupa": "MIĘSO I WĘDLINY UKRAINA",
    "Producent": "SALTOWSKI",
    "Kod Ean": "5906747117757",
    "x": "KIELBASA SALTOWSKI 300G SERWELAT UKRAINSKI UKRAINA"
  },
  {
    "INDEKS": "57699",
    "NAZWA": "ROSHEN HERBATNIKI 370G O SMAKU MLEKA SKONDENSOWANEGO UKRAINA",
    "RANKING": "51",
    "Grupa": "SŁODYCZE UKRAINA",
    "Producent": "ROSHEN",
    "Kod Ean": "4823077623790",
    "x": "HERBATNIKI ROSHEN 370G O SMAKU MLEKA SKONDENSOWANEGO UKRAINA"
  },
  {
    "INDEKS": "54297",
    "NAZWA": "NATAKHTARI LEMONIADA GRUZINSKA 0,5L SZKLO O SMAKU GRUSZKOWYM UKRAINA",
    "RANKING": "52",
    "Grupa": "NAPOJE BEZALKOHOLOWE UKRAINA",
    "Producent": "NATAKHTARI",
    "Kod Ean": "4860001124138",
    "x": "LEMONIADA GRUZINSKA NATAKHTARI 0,5L SZKLO O SMAKU GRUSZKOWYM UKRAINA"
  },
  {
    "INDEKS": "59673",
    "NAZWA": "YAW SUCHARKI 85G ROYAL CRAB UKRAINA",
    "RANKING": "53",
    "Grupa": "PRZEKĄSKI UKRAINA",
    "Producent": "YAW!",
    "Kod Ean": "4841900001188",
    "x": "SUCHARKI YAW 85G ROYAL CRAB UKRAINA"
  },
  {
    "INDEKS": "59676",
    "NAZWA": "YAW SUCHARKI 85G SALAMI UKRAINA",
    "RANKING": "54",
    "Grupa": "PRZEKĄSKI UKRAINA",
    "Producent": "YAW!",
    "Kod Ean": "4841900001270",
    "x": "SUCHARKI YAW 85G SALAMI UKRAINA"
  },
  {
    "INDEKS": "59669",
    "NAZWA": "YAW SUCHARKI 50G BARBECUE UKRAINA",
    "RANKING": "55",
    "Grupa": "PRZEKĄSKI UKRAINA",
    "Producent": "YAW!",
    "Kod Ean": "4841900002093",
    "x": "SUCHARKI YAW 50G BARBECUE UKRAINA"
  },
  {
    "INDEKS": "53027",
    "NAZWA": "SALTOWSKI SALAMI 300G STAROKIJOWSKIE UKRAINA",
    "RANKING": "57",
    "Grupa": "MIĘSO I WĘDLINY UKRAINA",
    "Producent": "SALTOWSKI",
    "Kod Ean": "5906747117719",
    "x": "SALAMI SALTOWSKI 300G STAROKIJOWSKIE UKRAINA"
  },
  {
    "INDEKS": "52430",
    "NAZWA": "SAN SANYCZ NASIONA SLONECZNIKA 80G PRAZONE UKRAINA",
    "RANKING": "58",
    "Grupa": "PRZEKĄSKI UKRAINA",
    "Producent": "SAN SANYCZ",
    "Kod Ean": "4820182068959",
    "x": "NASIONA SLONECZNIKA SAN SANYCZ 80G PRAZONE UKRAINA"
  },
  {
    "INDEKS": "54132",
    "NAZWA": "SLADOSVIT MLEKO SKONDENSOWANE 290G DOYPACK IMPERIAL PLUS UKRAINA",
    "RANKING": "59",
    "Grupa": "PUSZKI I SŁOIKI CHŁODZONE UKRAINA",
    "Producent": "SLADOSVIT",
    "Kod Ean": "4820034600986",
    "x": "MLEKO SKONDENSOWANE SLADOSVIT 290G DOYPACK IMPERIAL PLUS UKRAINA"
  },
  {
    "INDEKS": "54172",
    "NAZWA": "NORSU CHALWA SLONECZNIKOWA MIX WANILIA MALINA MATCHA KASZTAN 180G UKRAINA",
    "RANKING": "60",
    "Grupa": "SŁODYCZE UKRAINA",
    "Producent": "NORSU",
    "Kod Ean": "4823108420879",
    "x": "CHALWA SLONECZNIKOWA MIX WANILIA MALINA MATCHA KASZTAN 180G UKRAINA NORSU"
  },
  {
    "INDEKS": "54843",
    "NAZWA": "TORCHYN KETCHUP DO SZASZLYKA 250G UKRAINA",
    "RANKING": "61",
    "Grupa": "DODATKI DO POTRAW UKRAINA",
    "Producent": "TORCHYN",
    "Kod Ean": "4820001316100",
    "x": "TORCHYN KETCHUP DO SZASZLYKA 250G UKRAINA"
  },
  {
    "INDEKS": "56234",
    "NAZWA": "RODYNA ZEFIR BIALO ROZOWY 360G UKRAINA",
    "RANKING": "63",
    "Grupa": "SŁODYCZE UKRAINA",
    "Producent": "RODYNA",
    "Kod Ean": "4820024388023",
    "x": "RODYNA ZEFIR BIALO ROZOWY 360G UKRAINA"
  },
  {
    "INDEKS": "59977",
    "NAZWA": "LUBYSTOK PRZYPRAWA DO MIESA 30G UKRAINA",
    "RANKING": "64",
    "Grupa": "PRZYPRAWY I DODATKI W PROSZKU UKRAINA",
    "Producent": "LIUBYSTOK",
    "Kod Ean": "4820076010057",
    "x": "PRZYPRAWA DO MIESA LUBYSTOK 30G UKRAINA"
  },
  {
    "INDEKS": "59980",
    "NAZWA": "LUBYSTOK PRZYPRAWA GRUZINSKA 25G UKRAINA",
    "RANKING": "65",
    "Grupa": "PRZYPRAWY I DODATKI W PROSZKU UKRAINA",
    "Producent": "LIUBYSTOK",
    "Kod Ean": "4820076010262",
    "x": "PRZYPRAWA GRUZINSKA LUBYSTOK 25G UKRAINA"
  },
  {
    "INDEKS": "53020",
    "NAZWA": "SALTOWSKI KIELBASA OK 0,6KG LIKARSKA W NATURALNEJ OSLONCE UKRAINA",
    "RANKING": "66",
    "Grupa": "MIĘSO I WĘDLINY UKRAINA",
    "Producent": "SALTOWSKI",
    "Kod Ean": "2607250",
    "x": "KIELBASA SALTOWSKI OK 0,6KG LIKARSKA W NATURALNEJ OSLONCE UKRAINA"
  },
  {
    "INDEKS": "59674",
    "NAZWA": "YAW SUCHARKI 85G SMIETANA Z CEBULKA UKRAINA",
    "RANKING": "67",
    "Grupa": "PRZEKĄSKI UKRAINA",
    "Producent": "YAW!",
    "Kod Ean": "4841900001287",
    "x": "SUCHARKI YAW 85G SMIETANA Z CEBULKA UKRAINA"
  },
  {
    "INDEKS": "59675",
    "NAZWA": "YAW SUCHARKI 85G PIZZA UKRAINA",
    "RANKING": "68",
    "Grupa": "PRZEKĄSKI UKRAINA",
    "Producent": "YAW!",
    "Kod Ean": "4841900001898",
    "x": "SUCHARKI YAW 85G PIZZA UKRAINA"
  },
  {
    "INDEKS": "52427",
    "NAZWA": "KLIM 250G GALARETKI FANTASY Z NADZIENIEM OWOWCOWYM UKRAINA",
    "RANKING": "69",
    "Grupa": "SŁODYCZE UKRAINA",
    "Producent": "KLIM",
    "Kod Ean": "4820272980840",
    "x": "KLIM 250G GALARETKI FANTASY Z NADZIENIEM OWOWCOWYM UKRAINA"
  },
  {
    "INDEKS": "56229",
    "NAZWA": "RODYNA ZEFIR BIALO ROZOWY 190G UKRAINA",
    "RANKING": "70",
    "Grupa": "SŁODYCZE UKRAINA",
    "Producent": "RODYNA",
    "Kod Ean": "4820024386326",
    "x": "RODYNA ZEFIR BIALO ROZOWY 190G UKRAINA"
  },
  {
    "INDEKS": "45339",
    "NAZWA": "FLINT GRZANKI 70G O SMAKU PIKANTNY POMIDOR UKRAINA",
    "RANKING": "72",
    "Grupa": "PRZEKĄSKI UKRAINA",
    "Producent": "FLINT",
    "Kod Ean": "4820182746932",
    "x": "GRZANKI FLINT 70G O SMAKU PIKANTNY POMIDOR UKRAINA"
  },
  {
    "INDEKS": "55773",
    "NAZWA": "LAKOMKA NASIONA SLONECZNIKA 150G PRAZONE SOLONE UKRAINA",
    "RANKING": "73",
    "Grupa": "PRZEKĄSKI UKRAINA",
    "Producent": "SNACK PRODUCTION",
    "Kod Ean": "4820253632386",
    "x": "NASIONA SLONECZNIKA LAKOMKA 150G PRAZONE SOLONE UKRAINA"
  },
  {
    "INDEKS": "59679",
    "NAZWA": "YAW SUCHARKI 120G PIZZA UKRAINA",
    "RANKING": "74",
    "Grupa": "PRZEKĄSKI UKRAINA",
    "Producent": "YAW!",
    "Kod Ean": "4841900001812",
    "x": "SUCHARKI YAW 120G PIZZA UKRAINA"
  },
  {
    "INDEKS": "56781",
    "NAZWA": "OLIS KETCHUP LAGODNY 250G UKRAINA",
    "RANKING": "77",
    "Grupa": "DODATKI DO POTRAW UKRAINA",
    "Producent": "OLIS",
    "Kod Ean": "4820015714367",
    "x": "OLIS KETCHUP LAGODNY 250G UKRAINA"
  },
  {
    "INDEKS": "59973",
    "NAZWA": "LUBYSTOK PRZYPRAWA DO PILAWU 30G UKRAINA",
    "RANKING": "78",
    "Grupa": "PRZYPRAWY I DODATKI W PROSZKU UKRAINA",
    "Producent": "LIUBYSTOK",
    "Kod Ean": "4820076010415",
    "x": "PRZYPRAWA DO PILAWU LUBYSTOK 30G UKRAINA"
  },
  {
    "INDEKS": "59976",
    "NAZWA": "LUBYSTOK PRZYPRAWA DO KURCZAKA 30G UKRAINA",
    "RANKING": "79",
    "Grupa": "PRZYPRAWY I DODATKI W PROSZKU UKRAINA",
    "Producent": "LIUBYSTOK",
    "Kod Ean": "4820076010026",
    "x": "PRZYPRAWA DO KURCZAKA LUBYSTOK 30G UKRAINA"
  },
  {
    "INDEKS": "48256",
    "NAZWA": "AVK 200G BAMBUK Z CZEKOLADA UKRAINA",
    "RANKING": "80",
    "Grupa": "SŁODYCZE UKRAINA",
    "Producent": "AVK",
    "Kod Ean": "4823105813568",
    "x": "AVK 200G BAMBUK Z CZEKOLADA UKRAINA"
  },
  {
    "INDEKS": "56228",
    "NAZWA": "KYIVKHLIB OBWARZANKI SUSZKI 420G Z MAKIEM UKRAINA",
    "RANKING": "81",
    "Grupa": "PRZEKĄSKI UKRAINA",
    "Producent": "Kyivkhlib",
    "Kod Ean": "4823117500920",
    "x": "OBWARZANKI SUSZKI KYIVKHLIB 420G Z MAKIEM UKRAINA"
  },
  {
    "INDEKS": "45332",
    "NAZWA": "FLINT SUCHARKI 70G O SMAKU SMIETANY Z ZIOLAMI UKRAINA",
    "RANKING": "82",
    "Grupa": "PRZEKĄSKI UKRAINA",
    "Producent": "FLINT",
    "Kod Ean": "4820182742835",
    "x": "SUCHARKI FLINT 70G O SMAKU SMIETANY Z ZIOLAMI UKRAINA"
  },
  {
    "INDEKS": "45891",
    "NAZWA": "BUBLINI OBWARZANKI Z MAKIEM 375G UKRAINA",
    "RANKING": "83",
    "Grupa": "PRZEKĄSKI UKRAINA",
    "Producent": "BUBLINI",
    "Kod Ean": "4820027551769",
    "x": "BUBLINI OBWARZANKI Z MAKIEM 375G UKRAINA"
  },
  {
    "INDEKS": "57862",
    "NAZWA": "ROSHEN CIASTKA 168G LOVITA Z NADZIENIEM WISNIOWO WANILIOWYM UKRAINA",
    "RANKING": "84",
    "Grupa": "SŁODYCZE UKRAINA",
    "Producent": "ROSHEN",
    "Kod Ean": "4823077634192",
    "x": "CIASTKA ROSHEN 168G LOVITA Z NADZIENIEM WISNIOWO WANILIOWYM UKRAINA"
  },
  {
    "INDEKS": "57863",
    "NAZWA": "ROSHEN CIASTKA 168G LOVITA Z NADZIENIEM TRUSKAWKOWYM UKRAINA",
    "RANKING": "85",
    "Grupa": "SŁODYCZE UKRAINA",
    "Producent": "ROSHEN",
    "Kod Ean": "4823077634741",
    "x": "CIASTKA ROSHEN 168G LOVITA Z NADZIENIEM TRUSKAWKOWYM UKRAINA"
  },
  {
    "INDEKS": "57874",
    "NAZWA": "ROSHEN PRALINY 122G CHERRY QUEEN UKRAINA",
    "RANKING": "86",
    "Grupa": "SŁODYCZE UKRAINA",
    "Producent": "ROSHEN",
    "Kod Ean": "4823077640049",
    "x": "PRALINY ROSHEN 122G CHERRY QUEEN UKRAINA"
  },
  {
    "INDEKS": "45893",
    "NAZWA": "BUBLINI OBWARZANKI Z SEZAMEM 375G UKRAINA",
    "RANKING": "87",
    "Grupa": "PRZEKĄSKI UKRAINA",
    "Producent": "BUBLINI",
    "Kod Ean": "4820027551752",
    "x": "BUBLINI OBWARZANKI Z SEZAMEM 375G UKRAINA"
  },
  {
    "INDEKS": "56233",
    "NAZWA": "RODYNA ZEFIR W POLEWIE 420G UKRAINA",
    "RANKING": "88",
    "Grupa": "SŁODYCZE UKRAINA",
    "Producent": "RODYNA",
    "Kod Ean": "4820024388146",
    "x": "RODYNA ZEFIR W POLEWIE 420G UKRAINA"
  },
  {
    "INDEKS": "56773",
    "NAZWA": "OLIS MAJONEZ STOLOVYY 300G UKRAINA",
    "RANKING": "89",
    "Grupa": "DODATKI DO POTRAW UKRAINA",
    "Producent": "OLIS",
    "Kod Ean": "4820015714763",
    "x": "OLIS MAJONEZ STOLOVYY 300G UKRAINA"
  },
  {
    "INDEKS": "59975",
    "NAZWA": "LUBYSTOK PRZYPRAWA DO MARCHWI PO KOREANSKU OSTRA 30G UKRAINA",
    "RANKING": "91",
    "Grupa": "PRZYPRAWY I DODATKI W PROSZKU UKRAINA",
    "Producent": "LIUBYSTOK",
    "Kod Ean": "4820076010729",
    "x": "PRZYPRAWA DO MARCHWI PO KOREANSKU OSTRA LUBYSTOK 30G UKRAINA"
  },
  {
    "INDEKS": "59978",
    "NAZWA": "LUBYSTOK PRZYPRAWA DO SZASZLYKOW 30G UKRAINA",
    "RANKING": "92",
    "Grupa": "PRZYPRAWY I DODATKI W PROSZKU UKRAINA",
    "Producent": "LIUBYSTOK",
    "Kod Ean": "4820076010019",
    "x": "PRZYPRAWA DO SZASZLYKOW LUBYSTOK 30G UKRAINA"
  },
  {
    "INDEKS": "54848",
    "NAZWA": "STEINHAUER CHRZAN Z CWIKLA 200G UKRAINA",
    "RANKING": "93",
    "Grupa": "DODATKI DO POTRAW UKRAINA",
    "Producent": "STEINHAUER",
    "Kod Ean": "4030011460209",
    "x": "STEINHAUER CHRZAN Z CWIKLA 200G UKRAINA"
  },
  {
    "INDEKS": "55747",
    "NAZWA": "NIZHYN ADZYKA NA OSTRO 300G UKRAINA",
    "RANKING": "95",
    "Grupa": "PUSZKI I SŁOIKI UKRAINA",
    "Producent": "NIŻYN",
    "Kod Ean": "4823006808229",
    "x": "NIZHYN ADZYKA NA OSTRO 300G UKRAINA"
  },
  {
    "INDEKS": "53019",
    "NAZWA": "SALTOWSKI KIELBASA 400G KRAKOWSKA UKRAINA",
    "RANKING": "96",
    "Grupa": "MIĘSO I WĘDLINY UKRAINA",
    "Producent": "SALTOWSKI",
    "Kod Ean": "5906747117894",
    "x": "KIELBASA SALTOWSKI 400G KRAKOWSKA UKRAINA"
  },
  {
    "INDEKS": "42380",
    "NAZWA": "DRUZHKOVSKAYA 200G CHALWA SLONECZNIKOWA Z ORZESZKAMI ZIEMNYMI UKRAINA",
    "RANKING": "97",
    "Grupa": "SŁODYCZE UKRAINA",
    "Producent": "DRUŽSKOVSKAYA",
    "Kod Ean": "4823092700964",
    "x": "DRUZHKOVSKAYA 200G CHALWA SLONECZNIKOWA Z ORZESZKAMI ZIEMNYMI UKRAINA"
  },
  {
    "INDEKS": "59982",
    "NAZWA": "LUBYSTOK PRZYPRAWA DO UDEK I SKRZYDELEK 30G GRILL EXPERT UKRAINA",
    "RANKING": "100",
    "Grupa": "PRZYPRAWY I DODATKI W PROSZKU UKRAINA",
    "Producent": "LIUBYSTOK",
    "Kod Ean": "4820159135714",
    "x": "PRZYPRAWA DO UDEK I SKRZYDELEK LUBYSTOK 30G GRILL EXPERT UKRAINA"
  },
  {
    "INDEKS": "48270",
    "NAZWA": "KLIM 240G GALARETKI CYTRYNKI Z NADZIENIEM CYTRYNOWYM I POMARANCZOWYM UKRAINA",
    "RANKING": "101",
    "Grupa": "SŁODYCZE UKRAINA",
    "Producent": "KLIM",
    "Kod Ean": "4820218091968",
    "x": "KLIM 240G GALARETKI CYTRYNKI Z NADZIENIEM CYTRYNOWYM I POMARANCZOWYM UKRAINA"
  },
  {
    "INDEKS": "54851",
    "NAZWA": "STEINHAUER CHRZAN PIKANTNY 200G UKRAINA",
    "RANKING": "102",
    "Grupa": "DODATKI DO POTRAW UKRAINA",
    "Producent": "STEINHAUER",
    "Kod Ean": "4030011460100",
    "x": "STEINHAUER CHRZAN PIKANTNY 200G UKRAINA"
  },
  {
    "INDEKS": "57870",
    "NAZWA": "ROSHEN ZELKI 70G YUMMI GUMMI BANANA LAND UKRAINA",
    "RANKING": "103",
    "Grupa": "SŁODYCZE UKRAINA",
    "Producent": "ROSHEN",
    "Kod Ean": "4823077638459",
    "x": "ZELKI ROSHEN 70G YUMMI GUMMI BANANA LAND UKRAINA"
  },
  {
    "INDEKS": "45889",
    "NAZWA": "BUBLINI OBWARZANKI 375G UKRAINA",
    "RANKING": "104",
    "Grupa": "PRZEKĄSKI UKRAINA",
    "Producent": "BUBLINI",
    "Kod Ean": "4820027551011",
    "x": "BUBLINI OBWARZANKI 375G UKRAINA"
  },
  {
    "INDEKS": "56777",
    "NAZWA": "OLIS SOS MAJONEZOWY SALATKOWY 300G UKRAINA",
    "RANKING": "106",
    "Grupa": "DODATKI DO POTRAW UKRAINA",
    "Producent": "OLIS",
    "Kod Ean": "4820015714756",
    "x": "OLIS SOS MAJONEZOWY SALATKOWY 300G UKRAINA"
  },
  {
    "INDEKS": "57725",
    "NAZWA": "BUISQUIT SCHOKOLAD CIASTECZKA ZABODAY-KA KREMOWE BISKIT 180G UKRAINA",
    "RANKING": "107",
    "Grupa": "SŁODYCZE UKRAINA",
    "Producent": "BISQUIT SCHOKOLAD",
    "Kod Ean": "4820002303901",
    "x": "CIASTECZKA ZABODAY-KA KREMOWE BISKIT 180G BUISQUIT SCHOKOLAD UKRAINA"
  },
  {
    "INDEKS": "54176",
    "NAZWA": "TERA CIASTKA KRUCHE MIX 550G UKRAINA",
    "RANKING": "109",
    "Grupa": "SŁODYCZE UKRAINA",
    "Producent": "TERA",
    "Kod Ean": "4820027553930",
    "x": "CIASTKA KRUCHE MIX 550G UKRAINA TERA"
  },
  {
    "INDEKS": "57861",
    "NAZWA": "ROSHEN CIASTKA 168G LOVITA Z NADZIENIEM JABLKOWO CYNAMONOWYM UKRAINA",
    "RANKING": "111",
    "Grupa": "SŁODYCZE UKRAINA",
    "Producent": "ROSHEN",
    "Kod Ean": "4823077634178",
    "x": "CIASTKA ROSHEN 168G LOVITA Z NADZIENIEM JABLKOWO CYNAMONOWYM UKRAINA"
  },
  {
    "INDEKS": "40280",
    "NAZWA": "ROSHEN CZEKOLADA BIALA Z BABELKAMI 80G UKRAINA",
    "RANKING": "113",
    "Grupa": "SŁODYCZE UKRAINA",
    "Producent": "ROSHEN",
    "Kod Ean": "4823077626364",
    "x": "CZEKOLADA BIALA Z BABELKAMI ROSHEN 80G UKRAINA"
  },
  {
    "INDEKS": "56782",
    "NAZWA": "OLIS KETCHUP Z CZOSNKIEM 220G UKRAINA",
    "RANKING": "114",
    "Grupa": "DODATKI DO POTRAW UKRAINA",
    "Producent": "OLIS",
    "Kod Ean": "4820287030455",
    "x": "OLIS KETCHUP Z CZOSNKIEM 220G UKRAINA"
  },
  {
    "INDEKS": "57628",
    "NAZWA": "NELLY NELINA SPORT PREMIUM CZEKOLADA MLECZNA 55G Z NADZIENIAMI O SMAKU TRUSKAWKI I SERNIKA UKRAINA",
    "RANKING": "115",
    "Grupa": "SŁODYCZE UKRAINA",
    "Producent": "NELLY",
    "Kod Ean": "8606018943784",
    "x": "NELINA SPORT PREMIUM CZEKOLADA MLECZNA NELLY 55G Z NADZIENIAMI O SMAKU TRUSKAWKI I SERNIKA UKRAINA"
  },
  {
    "INDEKS": "57679",
    "NAZWA": "ZLOTY WIEK CHALWA SLONECZNIKOWA ZLOTY WIEK WANILIOWA 500G MNLTH UKRAINA",
    "RANKING": "116",
    "Grupa": "SŁODYCZE UKRAINA",
    "Producent": "ZŁOTY WIEK",
    "Kod Ean": "4820026701264",
    "x": "CHALWA SLONECZNIKOWA ZLOTY WIEK WANILIOWA 500G ZLOTY WIEK UKRAINA"
  },
  {
    "INDEKS": "57866",
    "NAZWA": "ROSHEN CIASTKA 180G MULTICAKE Z KREMEM WANILIOWYM UKRAINA",
    "RANKING": "117",
    "Grupa": "SŁODYCZE UKRAINA",
    "Producent": "ROSHEN",
    "Kod Ean": "4823077609084",
    "x": "CIASTKA ROSHEN 180G MULTICAKE Z KREMEM WANILIOWYM UKRAINA"
  },
  {
    "INDEKS": "59974",
    "NAZWA": "LUBYSTOK PRZYPRAWA CHMELI SUNELI 25G UKRAINA",
    "RANKING": "118",
    "Grupa": "PRZYPRAWY I DODATKI W PROSZKU UKRAINA",
    "Producent": "LIUBYSTOK",
    "Kod Ean": "4820076010354",
    "x": "PRZYPRAWA CHMELI SUNELI LUBYSTOK 25G UKRAINA"
  },
  {
    "INDEKS": "59981",
    "NAZWA": "LUBYSTOK PRZYPRAWA DO MIESA I STEKOW 30G GRILL EXPERT UKRAINA",
    "RANKING": "119",
    "Grupa": "PRZYPRAWY I DODATKI W PROSZKU UKRAINA",
    "Producent": "LIUBYSTOK",
    "Kod Ean": "4820159135738",
    "x": "PRZYPRAWA DO MIESA I STEKOW LUBYSTOK 30G GRILL EXPERT UKRAINA"
  },
  {
    "INDEKS": "54901",
    "NAZWA": "TARAS KWAS CHLEBOWY CZARNY 1,5L UKRAINA",
    "RANKING": "120",
    "Grupa": "NAPOJE BEZALKOHOLOWE UKRAINA",
    "Producent": "KVAS TARAS",
    "Kod Ean": "4038745600335",
    "x": "KWAS CHLEBOWY CZARNY 1,5L UKRAINA TARAS"
  },
  {
    "INDEKS": "54303",
    "NAZWA": "NATAKHTARI LEMONIADA GRUZINSKA 1L PET O SMAKU GRUSZKOWYM UKRAINA",
    "RANKING": "121",
    "Grupa": "NAPOJE BEZALKOHOLOWE UKRAINA",
    "Producent": "NATAKHTARI",
    "Kod Ean": "4860001124183",
    "x": "LEMONIADA GRUZINSKA NATAKHTARI 1L PET O SMAKU GRUSZKOWYM UKRAINA"
  },
  {
    "INDEKS": "40292",
    "NAZWA": "ROSHEN CUKIERKI 1KG BIM BOM UKRAINA",
    "RANKING": "122",
    "Grupa": "SŁODYCZE UKRAINA",
    "Producent": "ROSHEN",
    "Kod Ean": "4823077604294",
    "x": "CUKIERKI ROSHEN 1KG BIM BOM UKRAINA"
  },
  {
    "INDEKS": "55752",
    "NAZWA": "NIZHYN PASTA Z BAKLAZANOW UKRAINSKA 450G UKRAINA",
    "RANKING": "123",
    "Grupa": "PUSZKI I SŁOIKI UKRAINA",
    "Producent": "NIŻYN",
    "Kod Ean": "4823006802135",
    "x": "NIZHYN PASTA Z BAKLAZANOW UKRAINSKA 450G UKRAINA"
  },
  {
    "INDEKS": "53023",
    "NAZWA": "SALTOWSKI KIELBASA 700G MOLOCZNA UKRAINA",
    "RANKING": "124",
    "Grupa": "MIĘSO I WĘDLINY UKRAINA",
    "Producent": "SALTOWSKI",
    "Kod Ean": "5906747117870",
    "x": "KIELBASA SALTOWSKI 700G MOLOCZNA UKRAINA"
  },
  {
    "INDEKS": "59972",
    "NAZWA": "LUBYSTOK PRZYPRAWA DO ZIEMNIAKOW 30G UKRAINA",
    "RANKING": "126",
    "Grupa": "PRZYPRAWY I DODATKI W PROSZKU UKRAINA",
    "Producent": "LIUBYSTOK",
    "Kod Ean": "4820076010224",
    "x": "PRZYPRAWA DO ZIEMNIAKOW LUBYSTOK 30G UKRAINA"
  },
  {
    "INDEKS": "54130",
    "NAZWA": "SLADOSVIT MLEKO SKONDENSOWANE 270G DOYPACK IMPERIAL PLUS UKRAINA",
    "RANKING": "127",
    "Grupa": "PUSZKI I SŁOIKI CHŁODZONE UKRAINA",
    "Producent": "SLADOSVIT",
    "Kod Ean": "4820034600719",
    "x": "MLEKO SKONDENSOWANE SLADOSVIT 270G DOYPACK IMPERIAL PLUS UKRAINA"
  },
  {
    "INDEKS": "54300",
    "NAZWA": "NATAKHTARI LEMONIADA GRUZINSKA 0,5L SZKLO O SMAKU RABARBARU UKRAINA",
    "RANKING": "128",
    "Grupa": "NAPOJE BEZALKOHOLOWE UKRAINA",
    "Producent": "NATAKHTARI",
    "Kod Ean": "4860001124176",
    "x": "LEMONIADA GRUZINSKA NATAKHTARI 0,5L SZKLO O SMAKU RABARBARU UKRAINA"
  },
  {
    "INDEKS": "54845",
    "NAZWA": "TORCHIN PRZYPRAWA UNIWERSALNA 10 WARZYWA 60G UKRAINA",
    "RANKING": "129",
    "Grupa": "PRZYPRAWY I DODATKI W PROSZKU UKRAINA",
    "Producent": "TORCHYN",
    "Kod Ean": "7613035846043",
    "x": "TORCHIN PRZYPRAWA UNIWERSALNA 10 WARZYWA 60G UKRAINA"
  },
  {
    "INDEKS": "57723",
    "NAZWA": "TORCHYN MAJONEZ EUROPEJSKI 300G UKRAINA",
    "RANKING": "130",
    "Grupa": "DODATKI DO POTRAW UKRAINA",
    "Producent": "TORCHYN",
    "Kod Ean": "4820001316001",
    "x": "MAJONEZ EUROPEJSKI 300G TORCHYN UKRAINA"
  },
  {
    "INDEKS": "57859",
    "NAZWA": "ROSHEN WAFELKI 140G KONAFETTO Z NADZIENIEM KAKAOWYM UKRAINA",
    "RANKING": "131",
    "Grupa": "SŁODYCZE UKRAINA",
    "Producent": "ROSHEN",
    "Kod Ean": "4823077633034",
    "x": "WAFELKI ROSHEN 140G KONAFETTO Z NADZIENIEM KAKAOWYM UKRAINA"
  },
  {
    "INDEKS": "58384",
    "NAZWA": "KONTI CUKIERKI KONTI ROMASHKA 500G UKRAINA",
    "RANKING": "132",
    "Grupa": "SŁODYCZE UKRAINA",
    "Producent": "KONTI",
    "Kod Ean": "4823088612974",
    "x": "CUKIERKI KONTI ROMASHKA 500G UKRAINA KONTI"
  },
  {
    "INDEKS": "55767",
    "NAZWA": "HROOM CHIPSY ZIEMNIACZANE 50G O SMAKU KRABA UKRAINA",
    "RANKING": "134",
    "Grupa": "PRZEKĄSKI UKRAINA",
    "Producent": "SNACK PRODUCTION",
    "Kod Ean": "4820182061646",
    "x": "CHIPSY ZIEMNIACZANE HROOM 50G O SMAKU KRABA UKRAINA"
  },
  {
    "INDEKS": "57864",
    "NAZWA": "ROSHEN CIASTKA 150G LOVITA KLASYCZNE Z ORZECHAMI UKRAINA",
    "RANKING": "135",
    "Grupa": "SŁODYCZE UKRAINA",
    "Producent": "ROSHEN",
    "Kod Ean": "4823077633348",
    "x": "CIASTKA ROSHEN 150G LOVITA KLASYCZNE Z ORZECHAMI UKRAINA"
  },
  {
    "INDEKS": "57871",
    "NAZWA": "ROSHEN ZELKI 70G YUMMI GUMMI CUPCAKES UKRAINA",
    "RANKING": "136",
    "Grupa": "SŁODYCZE UKRAINA",
    "Producent": "ROSHEN",
    "Kod Ean": "4823077638596",
    "x": "ZELKI ROSHEN 70G YUMMI GUMMI CUPCAKES UKRAINA"
  },
  {
    "INDEKS": "57878",
    "NAZWA": "ROSHEN ZELKI 70G YUMMI GUMMI FROZEN YOGO UKRAINA",
    "RANKING": "137",
    "Grupa": "SŁODYCZE UKRAINA",
    "Producent": "ROSHEN",
    "Kod Ean": "4823077636363",
    "x": "ZELKI ROSHEN 70G YUMMI GUMMI FROZEN YOGO UKRAINA"
  },
  {
    "INDEKS": "57879",
    "NAZWA": "ROSHEN ZELKI 70G YUMMI GUMMI MINI BEAR MIX UKRAINA",
    "RANKING": "138",
    "Grupa": "SŁODYCZE UKRAINA",
    "Producent": "ROSHEN",
    "Kod Ean": "4823077636349",
    "x": "ZELKI ROSHEN 70G YUMMI GUMMI MINI BEAR MIX UKRAINA"
  },
  {
    "INDEKS": "55751",
    "NAZWA": "NIZHYN PASTA Z CUKINII 450G UKRAINA",
    "RANKING": "141",
    "Grupa": "PUSZKI I SŁOIKI UKRAINA",
    "Producent": "NIŻYN",
    "Kod Ean": "4823006801862",
    "x": "NIZHYN PASTA Z CUKINII 450G UKRAINA"
  },
  {
    "INDEKS": "57867",
    "NAZWA": "ROSHEN CIASTKA 135G LOVITA JELLY COOKIES TRUSKAWKOWE UKRAINA",
    "RANKING": "143",
    "Grupa": "SŁODYCZE UKRAINA",
    "Producent": "ROSHEN",
    "Kod Ean": "4823077634277",
    "x": "CIASTKA ROSHEN 135G LOVITA JELLY COOKIES TRUSKAWKOWE UKRAINA"
  },
  {
    "INDEKS": "57626",
    "NAZWA": "NELLY CZEKOLADA MLECZNA 55G NELINA SPORT Z WAFLEM UKRAINA",
    "RANKING": "147",
    "Grupa": "SŁODYCZE UKRAINA",
    "Producent": "NELLY",
    "Kod Ean": "8606018943791",
    "x": "CZEKOLADA MLECZNA NELLY 55G NELINA SPORT Z WAFLEM UKRAINA"
  },
  {
    "INDEKS": "57629",
    "NAZWA": "NELLY NELINO CZEKOLADA MLECZNA 85G Z NADZIENIAMI O SMAKU TRUSKAWKOWYM I MLECZNYM UKRAINA",
    "RANKING": "148",
    "Grupa": "SŁODYCZE UKRAINA",
    "Producent": "NELLY",
    "Kod Ean": "8606018943777",
    "x": "NELINO CZEKOLADA MLECZNA NELLY 85G Z NADZIENIAMI O SMAKU TRUSKAWKOWYM I MLECZNYM UKRAINA"
  },
  {
    "INDEKS": "57631",
    "NAZWA": "NELLY NELINO CZEKOLADA MLECZNA 85G Z NADZIENIAMI O SMAKU MALINOWYM I MLECZNYM UKRAINA",
    "RANKING": "149",
    "Grupa": "SŁODYCZE UKRAINA",
    "Producent": "NELLY",
    "Kod Ean": "8606018943357",
    "x": "NELINO CZEKOLADA MLECZNA NELLY 85G Z NADZIENIAMI O SMAKU MALINOWYM I MLECZNYM UKRAINA"
  },
  {
    "INDEKS": "57632",
    "NAZWA": "NELLY NELINO CZEKOLADA MLECZNA 85G Z NADZIENIAMI O SMAKU TOFFI I MLECZNYM UKRAINA",
    "RANKING": "150",
    "Grupa": "SŁODYCZE UKRAINA",
    "Producent": "NELLY",
    "Kod Ean": "8606018943364",
    "x": "NELINO CZEKOLADA MLECZNA NELLY 85G Z NADZIENIAMI O SMAKU TOFFI I MLECZNYM UKRAINA"
  },
  {
    "INDEKS": "54840",
    "NAZWA": "TORCHYN ZAPRAWA DO BARSZCZU Z BURAKOW I POMIDOROW 220G UKRAINA",
    "RANKING": "151",
    "Grupa": "PUSZKI I SŁOIKI UKRAINA",
    "Producent": "TORCHYN",
    "Kod Ean": "4820001316445",
    "x": "TORCHYN ZAPRAWA DO BARSZCZU Z BURAKOW I POMIDOROW 220G UKRAINA"
  },
  {
    "INDEKS": "57698",
    "NAZWA": "STEINHAUER OBWARZANKI SUSZKI FLORA O SMAKU WANILIOWYM 300G UKRAINA",
    "RANKING": "152",
    "Grupa": "SŁODYCZE UKRAINA",
    "Producent": "STEINHAUER",
    "Kod Ean": "4030011760040",
    "x": "OBWARZANKI SUSZKI FLORA O SMAKU WANILIOWYM 300G STEINHAUER UKRAINA"
  },
  {
    "INDEKS": "58576",
    "NAZWA": "NON STOP BOOST NAPOJ ENERGETYCZNY 250ML UKRAINA",
    "RANKING": "153",
    "Grupa": "NAPOJE BEZALKOHOLOWE UKRAINA",
    "Producent": "LLC NEW PRODUCTS UKRAINE",
    "Kod Ean": "4820252120020",
    "x": "BOOST NAPOJ ENERGETYCZNY 250ML UKRAINA NON STOP"
  },
  {
    "INDEKS": "59893",
    "NAZWA": "OLIS MUSZTARDA 500G AMERYKANSKA UKRAINA",
    "RANKING": "154",
    "Grupa": "DODATKI DO POTRAW UKRAINA",
    "Producent": "OLIS",
    "Kod Ean": "4820015718785",
    "x": "MUSZTARDA OLIS 500G AMERYKANSKA UKRAINA"
  },
  {
    "INDEKS": "55755",
    "NAZWA": "NIZHYN POMIDORY CHERRY MARYNOWANE 450G UKRAINA",
    "RANKING": "155",
    "Grupa": "PUSZKI I SŁOIKI UKRAINA",
    "Producent": "NIŻYN",
    "Kod Ean": "4823006805549",
    "x": "NIZHYN POMIDORY CHERRY MARYNOWANE 450G UKRAINA"
  },
  {
    "INDEKS": "53022",
    "NAZWA": "SALTOWSKI KIELBASA 700G LUBITELSKA UKRAINA",
    "RANKING": "156",
    "Grupa": "MIĘSO I WĘDLINY UKRAINA",
    "Producent": "SALTOWSKI",
    "Kod Ean": "5906747117863",
    "x": "KIELBASA SALTOWSKI 700G LUBITELSKA UKRAINA"
  },
  {
    "INDEKS": "57860",
    "NAZWA": "ROSHEN WAFELKI 140G KONAFETTO Z NADZIENIEM WANILIOWYM UKRAINA",
    "RANKING": "159",
    "Grupa": "SŁODYCZE UKRAINA",
    "Producent": "ROSHEN",
    "Kod Ean": "4823077631863",
    "x": "WAFELKI ROSHEN 140G KONAFETTO Z NADZIENIEM WANILIOWYM UKRAINA"
  },
  {
    "INDEKS": "54191",
    "NAZWA": "DIZZI POPCORN OWOCOWY MIX 55G UKRAINA",
    "RANKING": "160",
    "Grupa": "PRZEKĄSKI UKRAINA",
    "Producent": "DIZZI",
    "Kod Ean": "4820201230312",
    "x": "DIZZI POPCORN OWOCOWY MIX 55G UKRAINA"
  },
  {
    "INDEKS": "54235",
    "NAZWA": "DIZZI POPCORN CZEKOLADOWY 55G UKRAINA",
    "RANKING": "162",
    "Grupa": "SŁODYCZE UKRAINA",
    "Producent": "DIZZI",
    "Kod Ean": "4820201230510",
    "x": "POPCORN CZEKOLADOWY 55G UKRAINA DIZZI"
  },
  {
    "INDEKS": "57880",
    "NAZWA": "ROSHEN ZELKI 70G YUMMI GUMMI FIZZY WORMS UKRAINA",
    "RANKING": "163",
    "Grupa": "SŁODYCZE UKRAINA",
    "Producent": "ROSHEN",
    "Kod Ean": "4823077636387",
    "x": "ZELKI ROSHEN 70G YUMMI GUMMI FIZZY WORMS UKRAINA"
  },
  {
    "INDEKS": "54279",
    "NAZWA": "DOBRIM LUDJAM CIASTKA OWSIANE ZNAMIANSKE 400G UKRAINA",
    "RANKING": "164",
    "Grupa": "SŁODYCZE UKRAINA",
    "Producent": "DOBRIM LUDJAM",
    "Kod Ean": "4820179162691",
    "x": "DOBRIM LUDJAM CIASTKA OWSIANE ZNAMIANSKE 400G UKRAINA"
  },
  {
    "INDEKS": "52442",
    "NAZWA": "CHIPSTERS CHIPSY ZIEMNIACZANE 60G O SMAKU SMIETANY Z ZIOLAMI UKRAINA",
    "RANKING": "165",
    "Grupa": "PRZEKĄSKI UKRAINA",
    "Producent": "FLINT",
    "Kod Ean": "4820182740060",
    "x": "CHIPSY ZIEMNIACZANE CHIPSTERS 60G O SMAKU SMIETANY Z ZIOLAMI UKRAINA"
  },
  {
    "INDEKS": "58507",
    "NAZWA": "NIZHYN ZIELONY GROSZEK W PUSZCE 420G UKRAINA",
    "RANKING": "166",
    "Grupa": "PUSZKI I SŁOIKI UKRAINA",
    "Producent": "NIZHYN",
    "Kod Ean": "4823006803651",
    "x": "ZIELONY GROSZEK W PUSZCE 420G UKRAINA NIZHYN"
  },
  {
    "INDEKS": "45401",
    "NAZWA": "NIZHYN MARYNOWANE POMIDORY 920G UKRAINA",
    "RANKING": "167",
    "Grupa": "PUSZKI I SŁOIKI UKRAINA",
    "Producent": "NIŻYN",
    "Kod Ean": "4823006800964",
    "x": "MARYNOWANE POMIDORY 920G UKRAINA NIZHYN"
  },
  {
    "INDEKS": "18981",
    "NAZWA": "ROSHEN PRALINY 145G ASSORTMENT ELEGANT UKRAINA",
    "RANKING": "168",
    "Grupa": "SŁODYCZE UKRAINA",
    "Producent": "ROSHEN",
    "Kod Ean": "4823077611933",
    "x": "PRALINY ROSHEN 145G ASSORTMENT ELEGANT UKRAINA"
  },
  {
    "INDEKS": "57717",
    "NAZWA": "FERMA SER BRYNDZA 35% TLUSZCZU 180G UKRAINA",
    "RANKING": "170",
    "Grupa": "POZOSTAŁE UKRAINA",
    "Producent": "FERMA",
    "Kod Ean": "4820272181582",
    "x": "SER BRYNDZA 35% TLUSZCZU 180G FERMA UKRAINA"
  },
  {
    "INDEKS": "59682",
    "NAZWA": "KYIVKHLIB OBWARZANKI SUSZKI 340G Z NADZIENIEM MORELOWYM UKRAINA",
    "RANKING": "171",
    "Grupa": "PRZEKĄSKI UKRAINA",
    "Producent": "Kyivkhlib",
    "Kod Ean": "4823117501019",
    "x": "OBWARZANKI SUSZKI KYIVKHLIB 340G Z NADZIENIEM MORELOWYM UKRAINA"
  },
  {
    "INDEKS": "53229",
    "NAZWA": "ROSHEN CUKIERKI 1KG CRAZY BEE FRUTTY UKRAINA",
    "RANKING": "176",
    "Grupa": "SŁODYCZE UKRAINA",
    "Producent": "ROSHEN",
    "Kod Ean": "4823077604492",
    "x": "CUKIERKI ROSHEN 1KG CRAZY BEE FRUTTY UKRAINA"
  },
  {
    "INDEKS": "54869",
    "NAZWA": "KONTIK CIASTECZKA KANAPKOWE O SMAKU ORZECHOWYM 90G UKRAINA",
    "RANKING": "177",
    "Grupa": "SŁODYCZE UKRAINA",
    "Producent": "KONTI",
    "Kod Ean": "4823088608540",
    "x": "KONTIK CIASTECZKA KANAPKOWE O SMAKU ORZECHOWYM 90G UKRAINA"
  },
  {
    "INDEKS": "55753",
    "NAZWA": "NIZHYN PASTA Z BAKLAZANOW UKRAINSKA 300G UKRAINA",
    "RANKING": "178",
    "Grupa": "PUSZKI I SŁOIKI UKRAINA",
    "Producent": "NIŻYN",
    "Kod Ean": "4823006808182",
    "x": "NIZHYN PASTA Z BAKLAZANOW UKRAINSKA 300G UKRAINA"
  },
  {
    "INDEKS": "55757",
    "NAZWA": "NIZHYN BAKLAZANY OSTRE Z PRZYPRAWAMI ORIENTALNYMI 460G UKRAINA",
    "RANKING": "179",
    "Grupa": "PUSZKI I SŁOIKI UKRAINA",
    "Producent": "NIŻYN",
    "Kod Ean": "4823006805280",
    "x": "NIZHYN BAKLAZANY OSTRE Z PRZYPRAWAMI ORIENTALNYMI 460G UKRAINA"
  },
  {
    "INDEKS": "57301",
    "NAZWA": "SALEKS CHUVS 30G BATON O SMKAU CZARNEJ PORZECZKI UKRAINA",
    "RANKING": "180",
    "Grupa": "SŁODYCZE UKRAINA",
    "Producent": "SALEKS",
    "Kod Ean": "4820280820541",
    "x": "CHUVS 30G BATON O SMKAU CZARNEJ PORZECZKI UKRAINA SALEKS"
  },
  {
    "INDEKS": "58516",
    "NAZWA": "LOVARE MIESZANKA HERBAT (2G X 24TOR) NIGHT BEAUTEA UKRAINA",
    "RANKING": "182",
    "Grupa": "NAPOJE GORĄCE UKRAINA",
    "Producent": "LOVARE",
    "Kod Ean": "4823115404381",
    "x": "MIESZANKA HERBAT (2G X 24TOR) NIGHT BEAUTEA UKRAINA LOVARE"
  },
  {
    "INDEKS": "58521",
    "NAZWA": "LOVARE HERBATA (2G X 24TOR) EARL GREY UKRAINA",
    "RANKING": "183",
    "Grupa": "NAPOJE GORĄCE UKRAINA",
    "Producent": "LOVARE",
    "Kod Ean": "4820198874841",
    "x": "HERBATA (2G X 24TOR) EARL GREY UKRAINA LOVARE"
  },
  {
    "INDEKS": "58577",
    "NAZWA": "NON STOP JUNGLE NAPOJ ENERGETYCZNY 250ML UKRAINA",
    "RANKING": "184",
    "Grupa": "NAPOJE BEZALKOHOLOWE UKRAINA",
    "Producent": "LLC NEW PRODUCTS UKRAINE",
    "Kod Ean": "4820097897224",
    "x": "JUNGLE NAPOJ ENERGETYCZNY 250ML UKRAINA NON STOP"
  },
  {
    "INDEKS": "45337",
    "NAZWA": "FLINT GRZANKI 70G O SMAKU CZOSNKU UKRAINA",
    "RANKING": "185",
    "Grupa": "PRZEKĄSKI UKRAINA",
    "Producent": "FLINT",
    "Kod Ean": "4820182743160",
    "x": "GRZANKI FLINT 70G O SMAKU CZOSNKU UKRAINA"
  },
  {
    "INDEKS": "40298",
    "NAZWA": "ROSHEN CUKIERKI 1KG MILKY SPLASH TOFFI UKRAINA",
    "RANKING": "187",
    "Grupa": "SŁODYCZE UKRAINA",
    "Producent": "ROSHEN",
    "Kod Ean": "4823077608810",
    "x": "CUKIERKI ROSHEN 1KG MILKY SPLASH TOFFI UKRAINA"
  },
  {
    "INDEKS": "53232",
    "NAZWA": "ROSHEN CUKIERKI 1KG COFFEELIKE UKRAINA",
    "RANKING": "189",
    "Grupa": "SŁODYCZE UKRAINA",
    "Producent": "ROSHEN",
    "Kod Ean": "4823077605376",
    "x": "CUKIERKI ROSHEN 1KG COFFEELIKE UKRAINA"
  },
  {
    "INDEKS": "54302",
    "NAZWA": "NATAKHTARI LEMONIADA GRUZINSKA 1L PET O SMAKU ESTRAGONU UKRAINA",
    "RANKING": "190",
    "Grupa": "NAPOJE BEZALKOHOLOWE UKRAINA",
    "Producent": "NATAKHTARI",
    "Kod Ean": "4860001124190",
    "x": "LEMONIADA GRUZINSKA NATAKHTARI 1L PET O SMAKU ESTRAGONU UKRAINA"
  },
  {
    "INDEKS": "57868",
    "NAZWA": "ROSHEN ZELKI 70G YUMMI GUMMI FUNNY COLA UKRAINA",
    "RANKING": "191",
    "Grupa": "SŁODYCZE UKRAINA",
    "Producent": "ROSHEN",
    "Kod Ean": "4823077636394",
    "x": "ZELKI ROSHEN 70G YUMMI GUMMI FUNNY COLA UKRAINA"
  },
  {
    "INDEKS": "57869",
    "NAZWA": "ROSHEN ZELKI 70G YUMMI GUMMI DONUTS UKRAINA",
    "RANKING": "192",
    "Grupa": "SŁODYCZE UKRAINA",
    "Producent": "ROSHEN",
    "Kod Ean": "4823077636370",
    "x": "ZELKI ROSHEN 70G YUMMI GUMMI DONUTS UKRAINA"
  },
  {
    "INDEKS": "45335",
    "NAZWA": "FLINT SUCHARKI 70G O SMAKU KIELBAS MYSLIWSKICH UKRAINA",
    "RANKING": "193",
    "Grupa": "PRZEKĄSKI UKRAINA",
    "Producent": "FLINT",
    "Kod Ean": "4820182743030",
    "x": "SUCHARKI FLINT 70G O SMAKU KIELBAS MYSLIWSKICH UKRAINA"
  },
  {
    "INDEKS": "58382",
    "NAZWA": "KONTI CUKIERKI DZECK 290G UKRAINA",
    "RANKING": "196",
    "Grupa": "SŁODYCZE UKRAINA",
    "Producent": "KONTI",
    "Kod Ean": "4823088609646",
    "x": "CUKIERKI DZECK 290G UKRAINA KONTI"
  },
  {
    "INDEKS": "53246",
    "NAZWA": "ROSHEN CUKIERKI 1KG KROCK SLONY KARMEL Z ORZESZKAMI UKRAINA",
    "RANKING": "197",
    "Grupa": "SŁODYCZE UKRAINA",
    "Producent": "ROSHEN",
    "Kod Ean": "4823077634345",
    "x": "CUKIERKI ROSHEN 1KG KROCK SLONY KARMEL Z ORZESZKAMI UKRAINA"
  },
  {
    "INDEKS": "40285",
    "NAZWA": "ROSHEN CZEKOLADA MLECZNA 80G UKRAINA",
    "RANKING": "199",
    "Grupa": "SŁODYCZE UKRAINA",
    "Producent": "ROSHEN",
    "Kod Ean": "4823077626227",
    "x": "CZEKOLADA MLECZNA ROSHEN 80G UKRAINA"
  },
  {
    "INDEKS": "48274",
    "NAZWA": "KYIVKHLIB PIERNIKI 360G MLECZNE UKRAINA",
    "RANKING": "201",
    "Grupa": "SŁODYCZE UKRAINA",
    "Producent": "Kyivkhlib",
    "Kod Ean": "4823117506687",
    "x": "PIERNIKI KYIVKHLIB 360G MLECZNE UKRAINA"
  },
  {
    "INDEKS": "54641",
    "NAZWA": "VERES POMIDORY CHERRY MARYNOWANE 440G UKRAINA",
    "RANKING": "204",
    "Grupa": "PUSZKI I SŁOIKI UKRAINA",
    "Producent": "VERES",
    "Kod Ean": "4823105400737",
    "x": "POMIDORY CHERRY MARYNOWANE VERES 440G UKRAINA"
  },
  {
    "INDEKS": "55750",
    "NAZWA": "NIZHYN POMIDORY MIX Z ZURAWINA 920G UKRAINA",
    "RANKING": "206",
    "Grupa": "PUSZKI I SŁOIKI UKRAINA",
    "Producent": "NIŻYN",
    "Kod Ean": "4823006804955",
    "x": "NIZHYN POMIDORY MIX Z ZURAWINA 920G UKRAINA"
  },
  {
    "INDEKS": "55754",
    "NAZWA": "NIZHYN PASTA MAROKANSKA Z BAKLAZANAMI I PAPRYKA 300G UKRAINA",
    "RANKING": "207",
    "Grupa": "PUSZKI I SŁOIKI UKRAINA",
    "Producent": "NIŻYN",
    "Kod Ean": "4823006808069",
    "x": "NIZHYN PASTA MAROKANSKA Z BAKLAZANAMI I PAPRYKA 300G UKRAINA"
  },
  {
    "INDEKS": "57793",
    "NAZWA": "CHOCO LOCO CHALWA SLONECZNIKOWA 270G Z ORZESZKAMI ZIEMNYMI UKRAINA",
    "RANKING": "208",
    "Grupa": "SŁODYCZE UKRAINA",
    "Producent": "CHOCO LOCO",
    "Kod Ean": "5906412270008",
    "x": "CHALWA SLONECZNIKOWA CHOCO LOCO 270G Z ORZESZKAMI ZIEMNYMI UKRAINA"
  },
  {
    "INDEKS": "58388",
    "NAZWA": "KONTI CUKIERKI MONE 200G O SMAKU MLECZNYCH TRUFLI UKRAINA",
    "RANKING": "209",
    "Grupa": "SŁODYCZE UKRAINA",
    "Producent": "KONTI",
    "Kod Ean": "4823088604832",
    "x": "CUKIERKI MONE 200G O SMAKU MLECZNYCH TRUFLI UKRAINA KONTI"
  },
  {
    "INDEKS": "58504",
    "NAZWA": "NIZHYN SALATKA WARZYWNA OSTRO-SLODKI MIX 460G UKRAINA",
    "RANKING": "210",
    "Grupa": "PUSZKI I SŁOIKI UKRAINA",
    "Producent": "NIZHYN",
    "Kod Ean": "4823006805327",
    "x": "SALATKA WARZYWNA OSTRO-SLODKI MIX 460G UKRAINA NIZHYN"
  },
  {
    "INDEKS": "58505",
    "NAZWA": "NIZHYN SLODKA KUKURYDZA W PUSZCE 340G UKRAINA",
    "RANKING": "211",
    "Grupa": "PUSZKI I SŁOIKI UKRAINA",
    "Producent": "NIZHYN",
    "Kod Ean": "4823006807352",
    "x": "SLODKA KUKURYDZA W PUSZCE 340G UKRAINA NIZHYN"
  },
  {
    "INDEKS": "58519",
    "NAZWA": "LOVARE MIESZANKA HERBAT Z DODATKAMI (1,5G X 24TOR) UKRAINA",
    "RANKING": "212",
    "Grupa": "NAPOJE GORĄCE UKRAINA",
    "Producent": "LOVARE",
    "Kod Ean": "4820198872748",
    "x": "MIESZANKA HERBAT Z DODATKAMI (1,5G X 24TOR) UKRAINA LOVARE"
  },
  {
    "INDEKS": "58520",
    "NAZWA": "LOVARE HERBATA (2G X 24TOR) GOLDEN CEYLON UKRAINA",
    "RANKING": "213",
    "Grupa": "NAPOJE GORĄCE UKRAINA",
    "Producent": "LOVARE",
    "Kod Ean": "4820198874827",
    "x": "HERBATA (2G X 24TOR) GOLDEN CEYLON UKRAINA LOVARE"
  },
  {
    "INDEKS": "59876",
    "NAZWA": "PROTELINE BATON 100G KOKOSOWY RIF UKRAINA",
    "RANKING": "214",
    "Grupa": "SŁODYCZE UKRAINA",
    "Producent": "RIF",
    "Kod Ean": "4820200895819",
    "x": "BATON PROTELINE 100G KOKOSOWY RIF UKRAINA"
  },
  {
    "INDEKS": "18983",
    "NAZWA": "ROSHEN PRALINY 154G ASSORTMENT CLASSIC UKRAINA",
    "RANKING": "215",
    "Grupa": "SŁODYCZE UKRAINA",
    "Producent": "ROSHEN",
    "Kod Ean": "4823077611940",
    "x": "PRALINY ROSHEN 154G ASSORTMENT CLASSIC UKRAINA"
  },
  {
    "INDEKS": "56215",
    "NAZWA": "BISCOTTI CIASTKA KAKAOWE 160G UKRAINA",
    "RANKING": "216",
    "Grupa": "SŁODYCZE UKRAINA",
    "Producent": "BISCOTTI",
    "Kod Ean": "4820180813827",
    "x": "BISCOTTI CIASTKA KAKAOWE 160G UKRAINA"
  },
  {
    "INDEKS": "57697",
    "NAZWA": "HOMKA SLONECZNIK CZARNY PRAZONY SOLONY 230G UKRAINA",
    "RANKING": "217",
    "Grupa": "PRZEKĄSKI UKRAINA",
    "Producent": "HOMKA",
    "Kod Ean": "4820134943778",
    "x": "SLONECZNIK CZARNY PRAZONY SOLONY 230G HOMKA UKRAINA"
  },
  {
    "INDEKS": "40484",
    "NAZWA": "AVK 124G CUKIERKI TRUFLE SERCE - TRUFALIE SWEETS UKRAINA",
    "RANKING": "219",
    "Grupa": "SŁODYCZE UKRAINA",
    "Producent": "AVK",
    "Kod Ean": "4823105801466",
    "x": "AVK 124G CUKIERKI TRUFLE SERCE - TRUFALIE SWEETS UKRAINA"
  },
  {
    "INDEKS": "53037",
    "NAZWA": "SALTOWSKI USZY WEDZONE OK 0,3KG UKRAINA",
    "RANKING": "220",
    "Grupa": "MIĘSO I WĘDLINY UKRAINA",
    "Producent": "SALTOWSKI",
    "Kod Ean": "2602630",
    "x": "USZY WEDZONE SALTOWSKI OK 0,3KG UKRAINA"
  },
  {
    "INDEKS": "53239",
    "NAZWA": "ROSHEN CUKIERKI 1KG YOGURTINI UKRAINA",
    "RANKING": "221",
    "Grupa": "SŁODYCZE UKRAINA",
    "Producent": "ROSHEN",
    "Kod Ean": "4823077627200",
    "x": "CUKIERKI ROSHEN 1KG YOGURTINI UKRAINA"
  },
  {
    "INDEKS": "54247",
    "NAZWA": "MARIA KOZINAKI SLONECZNIKOWE 450G UKRAINA",
    "RANKING": "224",
    "Grupa": "SŁODYCZE UKRAINA",
    "Producent": "MARIA",
    "Kod Ean": "4820141658146",
    "x": "MARIA KOZINAKI SLONECZNIKOWE 450G UKRAINA"
  },
  {
    "INDEKS": "54775",
    "NAZWA": "NIZHYN RATATOUILLE 450G UKRAINA",
    "RANKING": "225",
    "Grupa": "KUCHNIA DANIA GOTOWE UKRAINA",
    "Producent": "NIŻYN",
    "Kod Ean": "4823006803873",
    "x": "NIZHYN RATATOUILLE 450G UKRAINA"
  },
  {
    "INDEKS": "54828",
    "NAZWA": "STEINHAUER MLEKO SKONDENSOWANE GOTOWANE SGUSZCZONKA 397G UKRAINA",
    "RANKING": "226",
    "Grupa": "PUSZKI I SŁOIKI UKRAINA",
    "Producent": "STEINHAUER",
    "Kod Ean": "4030011300123",
    "x": "STEINHAUER MLEKO SKONDENSOWANE GOTOWANE SGUSZCZONKA 397G UKRAINA"
  },
  {
    "INDEKS": "54837",
    "NAZWA": "STEINHAUER MARYNOWANE POMIDORY CHERSONSKIE 850ML UKRAINA",
    "RANKING": "227",
    "Grupa": "PUSZKI I SŁOIKI UKRAINA",
    "Producent": "STEINHAUER",
    "Kod Ean": "4030011500066",
    "x": "STEINHAUER MARYNOWANE POMIDORY CHERSONSKIE 850ML UKRAINA"
  },
  {
    "INDEKS": "55748",
    "NAZWA": "NIZHYN BAKLAZANY ZE SLIWKAMI 460G UKRAINA",
    "RANKING": "228",
    "Grupa": "PUSZKI I SŁOIKI UKRAINA",
    "Producent": "NIŻYN",
    "Kod Ean": "4823006805051",
    "x": "NIZHYN BAKLAZANY ZE SLIWKAMI 460G UKRAINA"
  },
  {
    "INDEKS": "55756",
    "NAZWA": "NIZHYN PAPRYKA MARYNOWANA Z PRZYPRAWAMI 450G UKRAINA",
    "RANKING": "229",
    "Grupa": "PUSZKI I SŁOIKI UKRAINA",
    "Producent": "NIŻYN",
    "Kod Ean": "4823006805808",
    "x": "NIZHYN PAPRYKA MARYNOWANA Z PRZYPRAWAMI 450G UKRAINA"
  },
  {
    "INDEKS": "56201",
    "NAZWA": "BISCOTTI CIASTKA NO BO TAK 550G UKRAINA",
    "RANKING": "231",
    "Grupa": "SŁODYCZE UKRAINA",
    "Producent": "BISCOTTI",
    "Kod Ean": "5906412270299",
    "x": "BISCOTTI CIASTKA NO BO TAK 550G UKRAINA"
  },
  {
    "INDEKS": "57794",
    "NAZWA": "CHOCO LOCO CHALWA SLONECZNIKOWA 500G O SMAKU WANILIOWYM UKRAINA",
    "RANKING": "233",
    "Grupa": "SŁODYCZE UKRAINA",
    "Producent": "CHOCO LOCO",
    "Kod Ean": "5905261906939",
    "x": "CHALWA SLONECZNIKOWA CHOCO LOCO 500G O SMAKU WANILIOWYM UKRAINA"
  },
  {
    "INDEKS": "57795",
    "NAZWA": "CHOCO LOCO CHALWA SLONECZNIKOWA 500G Z ORZESZKAMI ZIEMNYMI UKRAINA",
    "RANKING": "234",
    "Grupa": "SŁODYCZE UKRAINA",
    "Producent": "CHOCO LOCO",
    "Kod Ean": "5905261906946",
    "x": "CHALWA SLONECZNIKOWA CHOCO LOCO 500G Z ORZESZKAMI ZIEMNYMI UKRAINA"
  },
  {
    "INDEKS": "58575",
    "NAZWA": "NON STOP NAPOJ ENERGETYCZNY 250ML UKRAINA",
    "RANKING": "236",
    "Grupa": "NAPOJE BEZALKOHOLOWE UKRAINA",
    "Producent": "LLC NEW PRODUCTS UKRAINE",
    "Kod Ean": "4820097890317",
    "x": "NAPOJ ENERGETYCZNY 250ML UKRAINA NON STOP"
  },
  {
    "INDEKS": "59894",
    "NAZWA": "OLIS SOS BBQ 500G UKRAINA",
    "RANKING": "237",
    "Grupa": "DODATKI DO POTRAW UKRAINA",
    "Producent": "OLIS",
    "Kod Ean": "4820015718808",
    "x": "SOS BBQ OLIS 500G UKRAINA"
  },
  {
    "INDEKS": "57722",
    "NAZWA": "SZCZEDRO MAJONEZ SZCZEDRO PROVANSAL TLUSZCZU 67% 900G UKRAINA",
    "RANKING": "239",
    "Grupa": "DODATKI DO POTRAW UKRAINA",
    "Producent": "SZCZEDRO",
    "Kod Ean": "4823097400838",
    "x": "MAJONEZ SZCZEDRO PROVANSAL TLUSZCZU 67% 900G SZCZEDRO UKRAINA"
  },
  {
    "INDEKS": "53033",
    "NAZWA": "SALTOWSKI KIELBASA OK 0,6KG STOLICZNA W NATURALNEJ OSLONCE UKRAINA",
    "RANKING": "240",
    "Grupa": "MIĘSO I WĘDLINY UKRAINA",
    "Producent": "SALTOWSKI",
    "Kod Ean": "2607900",
    "x": "KIELBASA SALTOWSKI OK 0,6KG STOLICZNA W NATURALNEJ OSLONCE UKRAINA"
  },
  {
    "INDEKS": "45331",
    "NAZWA": "FLINT SUCHARKI 70G O SMAKU SERA UKRAINA",
    "RANKING": "242",
    "Grupa": "PRZEKĄSKI UKRAINA",
    "Producent": "FLINT",
    "Kod Ean": "4820182742927",
    "x": "SUCHARKI FLINT 70G O SMAKU SERA UKRAINA"
  },
  {
    "INDEKS": "59895",
    "NAZWA": "LUKS CHIPSY 125G SMIETANA I CEBULA MONDELEZ UKRAINA",
    "RANKING": "243",
    "Grupa": "PRZEKĄSKI UKRAINA",
    "Producent": "LUKS",
    "Kod Ean": "7622202224492",
    "x": "CHIPSY LUKS 125G SMIETANA I CEBULA MONDELEZ UKRAINA"
  },
  {
    "INDEKS": "59898",
    "NAZWA": "LUKS CHIPSY 125G ZIOLOWO SMIETANOWE MONDELEZ UKRAINA",
    "RANKING": "244",
    "Grupa": "PRZEKĄSKI UKRAINA",
    "Producent": "LUKS",
    "Kod Ean": "7622202268069",
    "x": "CHIPSY LUKS 125G ZIOLOWO SMIETANOWE MONDELEZ UKRAINA"
  },
  {
    "INDEKS": "56208",
    "NAZWA": "BISCOTTI BAKERY RASINS MINI CIASTKA Z RODZYNKAMI 150G UKRAINA",
    "RANKING": "245",
    "Grupa": "SŁODYCZE UKRAINA",
    "Producent": "BISCOTTI",
    "Kod Ean": "4820216120165",
    "x": "BISCOTTI BAKERY RASINS MINI CIASTKA Z RODZYNKAMI 150G UKRAINA"
  },
  {
    "INDEKS": "56210",
    "NAZWA": "BISCOTTI BAKERY PEANUTS MINI CIASTKA Z ORZESZKAMI ZIEMNYMI 150G UKRAINA",
    "RANKING": "246",
    "Grupa": "SŁODYCZE UKRAINA",
    "Producent": "BISCOTTI",
    "Kod Ean": "4820216120158",
    "x": "BISCOTTI BAKERY PEANUTS MINI CIASTKA Z ORZESZKAMI ZIEMNYMI 150G UKRAINA"
  },
  {
    "INDEKS": "40302",
    "NAZWA": "ROSHEN CUKIERKI 1KG SWEET DROP UKRAINA",
    "RANKING": "248",
    "Grupa": "SŁODYCZE UKRAINA",
    "Producent": "ROSHEN",
    "Kod Ean": "4823077604591",
    "x": "CUKIERKI ROSHEN 1KG SWEET DROP UKRAINA"
  },
  {
    "INDEKS": "42381",
    "NAZWA": "DRUZHKOVSKAYA 400G CHALWA SLONECZNIKOWA UKRAINA",
    "RANKING": "250",
    "Grupa": "SŁODYCZE UKRAINA",
    "Producent": "DRUŽSKOVSKAYA",
    "Kod Ean": "4823092701343",
    "x": "DRUZHKOVSKAYA 400G CHALWA SLONECZNIKOWA UKRAINA"
  },
  {
    "INDEKS": "43066",
    "NAZWA": "KONTI SUFLET KLASYCZNY BONJOUR 232G UKRAINA",
    "RANKING": "251",
    "Grupa": "SŁODYCZE UKRAINA",
    "Producent": "KONTI",
    "Kod Ean": "4823088608212",
    "x": "KONTI SUFLET KLASYCZNY BONJOUR 232G UKRAINA"
  },
  {
    "INDEKS": "56783",
    "NAZWA": "OLIS PASTA POMIDOROWA SMACHNOGO 250G UKRAINA",
    "RANKING": "254",
    "Grupa": "DODATKI DO POTRAW UKRAINA",
    "Producent": "OLIS",
    "Kod Ean": "4820287030349",
    "x": "OLIS PASTA POMIDOROWA SMACHNOGO 250G UKRAINA"
  },
  {
    "INDEKS": "57625",
    "NAZWA": "NELLY NELINA SPORT PREMIUM CZEKOLADA MLECZNA 50G Z ORZECHAMI LASKOWYMI UKRAINA",
    "RANKING": "255",
    "Grupa": "SŁODYCZE UKRAINA",
    "Producent": "NELLY",
    "Kod Ean": "8606018944903",
    "x": "NELINA SPORT PREMIUM CZEKOLADA MLECZNA NELLY 50G Z ORZECHAMI LASKOWYMI UKRAINA"
  },
  {
    "INDEKS": "59877",
    "NAZWA": "PROTELINE BATON 100G KARMEL Z ORZESZKAMI ZIEMNYMI RIF UKRAINA",
    "RANKING": "256",
    "Grupa": "SŁODYCZE UKRAINA",
    "Producent": "RIF",
    "Kod Ean": "4820200895833",
    "x": "BATON PROTELINE 100G KARMEL Z ORZESZKAMI ZIEMNYMI RIF UKRAINA"
  },
  {
    "INDEKS": "59878",
    "NAZWA": "PROTELINE BATON 100G KARMEL NUGAT RIF UKRAINA",
    "RANKING": "257",
    "Grupa": "SŁODYCZE UKRAINA",
    "Producent": "RIF",
    "Kod Ean": "4820200895857",
    "x": "BATON PROTELINE 100G KARMEL NUGAT RIF UKRAINA"
  },
  {
    "INDEKS": "59881",
    "NAZWA": "OLIS MAJONEZ 180G 50% SEROWY UKRAINA",
    "RANKING": "258",
    "Grupa": "DODATKI DO POTRAW UKRAINA",
    "Producent": "OLIS",
    "Kod Ean": "4820015716484",
    "x": "MAJONEZ OLIS 180G 50% SEROWY UKRAINA"
  },
  {
    "INDEKS": "59882",
    "NAZWA": "OLIS MAJONEZ 180G 30% GARLIC UKRAINA",
    "RANKING": "259",
    "Grupa": "DODATKI DO POTRAW UKRAINA",
    "Producent": "OLIS",
    "Kod Ean": "4820015716422",
    "x": "MAJONEZ OLIS 180G 30% GARLIC UKRAINA"
  },
  {
    "INDEKS": "59883",
    "NAZWA": "OLIS KETCHUP 250G SHASHLICHNIY UKRAINA",
    "RANKING": "260",
    "Grupa": "DODATKI DO POTRAW UKRAINA",
    "Producent": "OLIS",
    "Kod Ean": "4820015714350",
    "x": "KETCHUP OLIS 250G SHASHLICHNIY UKRAINA"
  },
  {
    "INDEKS": "45424",
    "NAZWA": "SAN SANYCZ NASIONA SLONECZNIKA 285G SOLONE PRAZONE UKRAINA",
    "RANKING": "262",
    "Grupa": "PRZEKĄSKI UKRAINA",
    "Producent": "SAN SANYCZ",
    "Kod Ean": "4823127308646",
    "x": "NASIONA SLONECZNIKA SAN SANYCZ 285G SOLONE PRAZONE UKRAINA"
  },
  {
    "INDEKS": "46378",
    "NAZWA": "SLADOSVIT MLEKO SKONDENSOWANE 500G GOTOWANE IMPERIAL PLUS UKRAINA",
    "RANKING": "263",
    "Grupa": "PUSZKI I SŁOIKI CHŁODZONE UKRAINA",
    "Producent": "SLADOSVIT",
    "Kod Ean": "4820034600764",
    "x": "MLEKO SKONDENSOWANE SLADOSVIT 500G GOTOWANE IMPERIAL PLUS UKRAINA"
  },
  {
    "INDEKS": "54868",
    "NAZWA": "KONTIK CIASTECZKA KANAPKOWE O SMAKU CZEKOLADOWYM 90G UKRAINA",
    "RANKING": "265",
    "Grupa": "SŁODYCZE UKRAINA",
    "Producent": "KONTI",
    "Kod Ean": "4823088608489",
    "x": "KONTIK CIASTECZKA KANAPKOWE O SMAKU CZEKOLADOWYM 90G UKRAINA"
  },
  {
    "INDEKS": "57300",
    "NAZWA": "SALEKS CHUVS 30G BATON O SMAKU MALINOWYM UKRAINA",
    "RANKING": "266",
    "Grupa": "SŁODYCZE UKRAINA",
    "Producent": "SALEKS",
    "Kod Ean": "4820280820916",
    "x": "CHUVS 30G BATON O SMAKU MALINOWYM UKRAINA SALEKS"
  },
  {
    "INDEKS": "57796",
    "NAZWA": "CHOCO LOCO COCOMALLOW 150G UKRAINA",
    "RANKING": "267",
    "Grupa": "SŁODYCZE UKRAINA",
    "Producent": "CHOCO LOCO",
    "Kod Ean": "5905261906496",
    "x": "COCOMALLOW CHOCO LOCO 150G UKRAINA"
  },
  {
    "INDEKS": "57816",
    "NAZWA": "CHOCO LOCO PUFLIKI JELLY 280G ANANASOWY UKRAINA",
    "RANKING": "268",
    "Grupa": "SŁODYCZE UKRAINA",
    "Producent": "CHOCO LOCO",
    "Kod Ean": "5906412270787",
    "x": "PUFLIKI JELLY CHOCO LOCO 280G ANANASOWY UKRAINA"
  },
  {
    "INDEKS": "58385",
    "NAZWA": "KONTI CUKIERKI KONTI MOUSSE 500G O SMAKU CAPPUCCINO UKRAINA",
    "RANKING": "269",
    "Grupa": "SŁODYCZE UKRAINA",
    "Producent": "KONTI",
    "Kod Ean": "4823088609103",
    "x": "CUKIERKI KONTI MOUSSE 500G O SMAKU CAPPUCCINO UKRAINA KONTI"
  },
  {
    "INDEKS": "58503",
    "NAZWA": "NIZHYN FASOLA W SOSIE POMIDOROWYM Z WARZYWAMI 450G UKRAINA",
    "RANKING": "270",
    "Grupa": "PUSZKI I SŁOIKI UKRAINA",
    "Producent": "NIZHYN",
    "Kod Ean": "4823006801947",
    "x": "FASOLA W SOSIE POMIDOROWYM Z WARZYWAMI 450G UKRAINA NIZHYN"
  },
  {
    "INDEKS": "58518",
    "NAZWA": "LOVARE MIESZANKA ZIOL. (1,5G X 24TOR) ROYAL DESSERT UKRAINA",
    "RANKING": "271",
    "Grupa": "NAPOJE GORĄCE UKRAINA",
    "Producent": "LOVARE",
    "Kod Ean": "4820198871123",
    "x": "MIESZANKA ZIOL. (1,5G X 24TOR) ROYAL DESSERT UKRAINA LOVARE"
  },
  {
    "INDEKS": "43063",
    "NAZWA": "KONTI DESER BONJOUR TRUSKAWKA ZE SMIETANKA 232G UKRAINA",
    "RANKING": "275",
    "Grupa": "SŁODYCZE UKRAINA",
    "Producent": "KONTI",
    "Kod Ean": "4823088608267",
    "x": "KONTI DESER BONJOUR TRUSKAWKA ZE SMIETANKA 232G UKRAINA"
  },
  {
    "INDEKS": "43068",
    "NAZWA": "KONTI DESER BONJOUR O SMAKU WISNIOWYM 232G UKRAINA",
    "RANKING": "276",
    "Grupa": "SŁODYCZE UKRAINA",
    "Producent": "BONJOUR",
    "Kod Ean": "4823088608243",
    "x": "KONTI DESER BONJOUR O SMAKU WISNIOWYM 232G UKRAINA"
  },
  {
    "INDEKS": "54642",
    "NAZWA": "VERES POMIDORY MARYNOWANE 780G UKRAINA",
    "RANKING": "278",
    "Grupa": "PUSZKI I SŁOIKI UKRAINA",
    "Producent": "VERES",
    "Kod Ean": "4823105405824",
    "x": "VERES POMIDORY MARYNOWANE 780G UKRAINA"
  },
  {
    "INDEKS": "57872",
    "NAZWA": "ROSHEN PRALINY 145G ASSORTMENT COMPLIMENT UKRAINA",
    "RANKING": "280",
    "Grupa": "SŁODYCZE UKRAINA",
    "Producent": "ROSHEN",
    "Kod Ean": "4823077625879",
    "x": "PRALINY ROSHEN 145G ASSORTMENT COMPLIMENT UKRAINA"
  },
  {
    "INDEKS": "57812",
    "NAZWA": "SALEKS CIASTKA USZKA 150G Z BIALYM DEKOREM UKRAINA",
    "RANKING": "281",
    "Grupa": "SŁODYCZE UKRAINA",
    "Producent": "SALEKS",
    "Kod Ean": "4820146148482",
    "x": "CIASTKA USZKA SALEKS 150G Z BIALYM DEKOREM UKRAINA"
  },
  {
    "INDEKS": "54133",
    "NAZWA": "SLADOSVIT MLEKO SKONDENSOWANE 370G GOTOWANE IMPERIAL PLUS UKRAINA",
    "RANKING": "283",
    "Grupa": "PUSZKI I SŁOIKI CHŁODZONE UKRAINA",
    "Producent": "SLADOSVIT",
    "Kod Ean": "4820034600979",
    "x": "MLEKO SKONDENSOWANE SLADOSVIT 370G GOTOWANE IMPERIAL PLUS UKRAINA"
  },
  {
    "INDEKS": "57805",
    "NAZWA": "CHOCO LOCO STROOPWAFEL SOLONY KARMEL 33G UKRAINA",
    "RANKING": "285",
    "Grupa": "SŁODYCZE UKRAINA",
    "Producent": "CHOCO LOCO",
    "Kod Ean": "5906412270107",
    "x": "CHOCO LOCO STROOPWAFEL SOLONY KARMEL 33G UKRAINA"
  },
  {
    "INDEKS": "59880",
    "NAZWA": "OLIS MAJONEZ 300G 67% PROVANSAL UKRAINA",
    "RANKING": "286",
    "Grupa": "DODATKI DO POTRAW UKRAINA",
    "Producent": "OLIS",
    "Kod Ean": "4820287030301",
    "x": "MAJONEZ OLIS 300G 67% PROVANSAL UKRAINA"
  },
  {
    "INDEKS": "40296",
    "NAZWA": "ROSHEN CUKIERKI 1KG KROWKA UKRAINA",
    "RANKING": "289",
    "Grupa": "SŁODYCZE UKRAINA",
    "Producent": "ROSHEN",
    "Kod Ean": "4823077602450",
    "x": "CUKIERKI ROSHEN 1KG KROWKA UKRAINA"
  },
  {
    "INDEKS": "40489",
    "NAZWA": "BOOMZA 170G POPCORN W KARMELU OWOCOWY UKRAINA",
    "RANKING": "291",
    "Grupa": "SŁODYCZE UKRAINA",
    "Producent": "BOOMZA",
    "Kod Ean": "4820196732044",
    "x": "BOOMZA 170G POPCORN W KARMELU OWOCOWY UKRAINA"
  },
  {
    "INDEKS": "42379",
    "NAZWA": "DRUZHKOVSKAYA 200G CHALWA SLONECZNIKOWA KAKAOWA UKRAINA",
    "RANKING": "292",
    "Grupa": "SŁODYCZE UKRAINA",
    "Producent": "DRUŽSKOVSKAYA",
    "Kod Ean": "4823092701022",
    "x": "DRUZHKOVSKAYA 200G CHALWA SLONECZNIKOWA KAKAOWA UKRAINA"
  },
  {
    "INDEKS": "43064",
    "NAZWA": "KONTI DESER BONJOUR O SMAKU JAGOD I MASCARPONE 232G UKRAINA",
    "RANKING": "293",
    "Grupa": "SŁODYCZE UKRAINA",
    "Producent": "KONTI",
    "Kod Ean": "4823088608281",
    "x": "KONTI DESER BONJOUR O SMAKU JAGOD I MASCARPONE 232G UKRAINA"
  },
  {
    "INDEKS": "53245",
    "NAZWA": "ROSHEN WAFELKI 1KG KONAFETTO BIANCO UKRAINA",
    "RANKING": "297",
    "Grupa": "SŁODYCZE UKRAINA",
    "Producent": "ROSHEN",
    "Kod Ean": "4823077635670",
    "x": "WAFELKI ROSHEN 1KG KONAFETTO BIANCO UKRAINA"
  },
  {
    "INDEKS": "54609",
    "NAZWA": "VERES PASTA Z BAKLAZANA 500G UKRAINA",
    "RANKING": "299",
    "Grupa": "PUSZKI I SŁOIKI UKRAINA",
    "Producent": "VERES",
    "Kod Ean": "4823105400577",
    "x": "VERES PASTA Z BAKLAZANA 500G UKRAINA"
  },
  {
    "INDEKS": "54618",
    "NAZWA": "VERES BAKLAZANY W SOSIE POMIDOROWYM SALSA 500G UKRAINA",
    "RANKING": "300",
    "Grupa": "PUSZKI I SŁOIKI UKRAINA",
    "Producent": "VERES",
    "Kod Ean": "4823105400713",
    "x": "VERES BAKLAZANY W SOSIE POMIDOROWYM SALSA 500G UKRAINA"
  },
  {
    "INDEKS": "56204",
    "NAZWA": "BISCOTTI CIASTKA ROMASHKA 550G UKRAINA",
    "RANKING": "303",
    "Grupa": "SŁODYCZE UKRAINA",
    "Producent": "BISCOTTI",
    "Kod Ean": "5906412270619",
    "x": "BISCOTTI CIASTKA ROMASHKA 550G UKRAINA"
  },
  {
    "INDEKS": "57687",
    "NAZWA": "STEINHAUER MARYNOWANE POMIDORY CHERSONSKIE 1,85KG MNLTH UKRAINA",
    "RANKING": "304",
    "Grupa": "PUSZKI I SŁOIKI UKRAINA",
    "Producent": "STEINHAUER",
    "Kod Ean": "4030011500516",
    "x": "MARYNOWANE POMIDORY CHERSONSKIE 1,85KG UKRAINA STEINHAUER"
  },
  {
    "INDEKS": "58387",
    "NAZWA": "KONTI CUKIERKI CREAM YOGHURT 500G O SMAKU WISNIOWYM UKRAINA",
    "RANKING": "305",
    "Grupa": "SŁODYCZE UKRAINA",
    "Producent": "KONTI",
    "Kod Ean": "4823088609189",
    "x": "CUKIERKI CREAM YOGHURT 500G O SMAKU WISNIOWYM UKRAINA KONTI"
  },
  {
    "INDEKS": "58512",
    "NAZWA": "LOVARE MIESZANKA HERBAT Z DODATKAMI (2G X 24TOR) 1001 NIGHTS UKRAINA",
    "RANKING": "306",
    "Grupa": "NAPOJE GORĄCE UKRAINA",
    "Producent": "LOVARE",
    "Kod Ean": "4820097816508",
    "x": "MIESZANKA HERBAT Z DODATKAMI (2G X 24TOR) 1001 NIGHTS UKRAINA LOVARE"
  },
  {
    "INDEKS": "58515",
    "NAZWA": "LOVARE MIESZANKA HERBAT Z DODATKAMI (2G X 24TOR) RASPBERRY VANILLA TEA UKRAINA",
    "RANKING": "307",
    "Grupa": "NAPOJE GORĄCE UKRAINA",
    "Producent": "LOVARE",
    "Kod Ean": "4820198872724",
    "x": "MIESZANKA HERBAT Z DODATKAMI (2G X 24TOR) RASPBERRY VANILLA TEA UKRAINA LOVARE"
  },
  {
    "INDEKS": "58522",
    "NAZWA": "LOVARE HERBATA (2G X 24TOR) ENGLISH TEA UKRAINA",
    "RANKING": "308",
    "Grupa": "NAPOJE GORĄCE UKRAINA",
    "Producent": "LOVARE",
    "Kod Ean": "4820097816065",
    "x": "HERBATA (2G X 24TOR) ENGLISH TEA UKRAINA LOVARE"
  },
  {
    "INDEKS": "57696",
    "NAZWA": "LAKOMKA HERBATNIKI ORESZKI Z MLEKIEM SKONDENSOWANYM 500G UKRAINA",
    "RANKING": "315",
    "Grupa": "SŁODYCZE UKRAINA",
    "Producent": "LAKOMKA",
    "Kod Ean": "4030011790290",
    "x": "HERBATNIKI ORESZKI Z MLEKIEM SKONDENSOWANYM 500G LAKOMKA UKRAINA"
  },
  {
    "INDEKS": "59892",
    "NAZWA": "OLIS MAJONEZ 500G 72% FAINYY UKRAINA",
    "RANKING": "316",
    "Grupa": "DODATKI DO POTRAW UKRAINA",
    "Producent": "OLIS",
    "Kod Ean": "4820015718822",
    "x": "MAJONEZ OLIS 500G 72% FAINYY UKRAINA"
  },
  {
    "INDEKS": "53240",
    "NAZWA": "ROSHEN CUKIERKI 1KG BUTTER MILK UKRAINA",
    "RANKING": "319",
    "Grupa": "SŁODYCZE UKRAINA",
    "Producent": "ROSHEN",
    "Kod Ean": "4823077628054",
    "x": "CUKIERKI ROSHEN 1KG BUTTER MILK UKRAINA"
  },
  {
    "INDEKS": "55700",
    "NAZWA": "KONTI DESER BONJOUR MIX CAPPUCCINO, JAGODY I MASCARPONE, TRUSKAWKOWO-SMIETANKOWY 348G UKRAINA",
    "RANKING": "320",
    "Grupa": "SŁODYCZE UKRAINA",
    "Producent": "KONTI",
    "Kod Ean": "4823088611427",
    "x": "KONTI DESER BONJOUR MIX CAPPUCCINO, JAGODY I MASCARPONE, TRUSKAWKOWO-SMIETANKOWY 348G UKRAINA"
  },
  {
    "INDEKS": "57876",
    "NAZWA": "ROSHEN CZEKOLADA 90G LACMI Z NADZIENIEM MLECZNYM I WAFELKIEM UKRAINA",
    "RANKING": "321",
    "Grupa": "SŁODYCZE UKRAINA",
    "Producent": "ROSHEN",
    "Kod Ean": "4823077633195",
    "x": "CZEKOLADA ROSHEN 90G LACMI Z NADZIENIEM MLECZNYM I WAFELKIEM UKRAINA"
  },
  {
    "INDEKS": "59879",
    "NAZWA": "OLIS MAJONEZ 560G 67% STOLOVYY UKRAINA",
    "RANKING": "322",
    "Grupa": "DODATKI DO POTRAW UKRAINA",
    "Producent": "OLIS",
    "Kod Ean": "4820015714893",
    "x": "MAJONEZ OLIS 560G 67% STOLOVYY UKRAINA"
  },
  {
    "INDEKS": "57877",
    "NAZWA": "ROSHEN CZEKOLADA Z BABELKAMI 85G LACMI Z NADZIENIEM MLECZNYM I PLATKAMI UKRAINA",
    "RANKING": "323",
    "Grupa": "SŁODYCZE UKRAINA",
    "Producent": "ROSHEN",
    "Kod Ean": "4823077634369",
    "x": "CZEKOLADA Z BABELKAMI ROSHEN 85G LACMI Z NADZIENIEM MLECZNYM I PLATKAMI UKRAINA"
  },
  {
    "INDEKS": "43072",
    "NAZWA": "KONTI DESER BONJOUR O SMAKU PANNA COTTA Z MALINAMI 232G UKRAINA",
    "RANKING": "324",
    "Grupa": "SŁODYCZE UKRAINA",
    "Producent": "KONTI",
    "Kod Ean": "4823088608304",
    "x": "KONTI DESER BONJOUR O SMAKU PANNA COTTA Z MALINAMI 232G UKRAINA"
  },
  {
    "INDEKS": "57685",
    "NAZWA": "MOHAPX SLONECZNIK PRAZONY JUMBO XXL 300G MNLTH UKRAINA",
    "RANKING": "326",
    "Grupa": "PRZEKĄSKI UKRAINA",
    "Producent": "MOHAPX",
    "Kod Ean": "8594181462044",
    "x": "SLONECZNIK PRAZONY JUMBO XXL 300G MOHAPX UKRAINA"
  },
  {
    "INDEKS": "57688",
    "NAZWA": "MOHAPX SLONECZNIK PRAZONY I SOLONY 300G MNLTH UKRAINA",
    "RANKING": "327",
    "Grupa": "PRZEKĄSKI UKRAINA",
    "Producent": "MOHAPX",
    "Kod Ean": "8594181462013",
    "x": "SLONECZNIK PRAZONY I SOLONY 300G MOHAPX UKRAINA"
  },
  {
    "INDEKS": "57690",
    "NAZWA": "MOHAPX SLONECZNIK PRAZONY I SOLONY JUMBO XXL 300G UKRAINA",
    "RANKING": "328",
    "Grupa": "PRZEKĄSKI UKRAINA",
    "Producent": "MOHAPX",
    "Kod Ean": "8594181462051",
    "x": "SLONECZNIK PRAZONY I SOLONY JUMBO XXL 300G MOHAPX UKRAINA"
  },
  {
    "INDEKS": "57806",
    "NAZWA": "SALEKS CHUVS 180G O SMAKU CZARNEJ PORZECZKI UKRAINA",
    "RANKING": "329",
    "Grupa": "SŁODYCZE UKRAINA",
    "Producent": "SALEKS",
    "Kod Ean": "4820280820572",
    "x": "CHUVS SALEKS 180G O SMAKU CZARNEJ PORZECZKI UKRAINA"
  },
  {
    "INDEKS": "57807",
    "NAZWA": "SALEKS CHUVS 180G O SMAKU MANGO UKRAINA",
    "RANKING": "330",
    "Grupa": "SŁODYCZE UKRAINA",
    "Producent": "SALEKS",
    "Kod Ean": "4820280820565",
    "x": "CHUVS SALEKS 180G O SMAKU MANGO UKRAINA"
  },
  {
    "INDEKS": "58993",
    "NAZWA": "MOHAPX SLONECZNIK PRAZONY 300G UKRAINA",
    "RANKING": "331",
    "Grupa": "PRZEKĄSKI UKRAINA",
    "Producent": "MOHAPX",
    "Kod Ean": "8594181462006",
    "x": "SLONECZNIK PRAZONY 300G UKRAINA MOHAPX"
  },
  {
    "INDEKS": "57712",
    "NAZWA": "MASHA AND THE BEAR CHRUPKI KUKURYDZIANE MASZA I NIEDZWIEDZ 160G UKRAINA",
    "RANKING": "338",
    "Grupa": "PRZEKĄSKI UKRAINA",
    "Producent": "MASHA AND THE BEAR",
    "Kod Ean": "4033443822072",
    "x": "CHRUPKI KUKURYDZIANE MASZA I NIEDZWIEDZ 160G MASHA AND THE BEAR UKRAINA"
  },
  {
    "INDEKS": "40488",
    "NAZWA": "BOOMZA 170G POPCORN W KARMELU UKRAINA",
    "RANKING": "340",
    "Grupa": "SŁODYCZE UKRAINA",
    "Producent": "BOOMZA",
    "Kod Ean": "4820196732006",
    "x": "BOOMZA 170G POPCORN W KARMELU UKRAINA"
  },
  {
    "INDEKS": "43073",
    "NAZWA": "KONTI CUKIERKI GOLDEN LILY TOFFE 1KG UKRAINA",
    "RANKING": "341",
    "Grupa": "SŁODYCZE UKRAINA",
    "Producent": "KONTI",
    "Kod Ean": "4823088604948",
    "x": "KONTI CUKIERKI GOLDEN LILY TOFFE 1KG UKRAINA"
  },
  {
    "INDEKS": "54647",
    "NAZWA": "VERES DZEM TRUSKAWKOWY 385G UKRAINA",
    "RANKING": "343",
    "Grupa": "PUSZKI I SŁOIKI UKRAINA",
    "Producent": "VERES",
    "Kod Ean": "4823105400348",
    "x": "VERES DZEM TRUSKAWKOWY 385G UKRAINA"
  },
  {
    "INDEKS": "54839",
    "NAZWA": "STEINHAUER POMIDORY KOKTAJLOWE KONSERWOWE 720ML UKRAINA",
    "RANKING": "344",
    "Grupa": "PUSZKI I SŁOIKI UKRAINA",
    "Producent": "STEINHAUER",
    "Kod Ean": "4030011500073",
    "x": "STEINHAUER POMIDORY KOKTAJLOWE KONSERWOWE 720ML UKRAINA"
  },
  {
    "INDEKS": "54854",
    "NAZWA": "BISQUIT SCHOKOLAD ROLADA BISZKOPTOWA O SMAKU CZEKOLADOWYM 290 G UKRAINA",
    "RANKING": "345",
    "Grupa": "SŁODYCZE UKRAINA",
    "Producent": "BISQUIT SCHOKOLAD",
    "Kod Ean": "4820002303789",
    "x": "BISQUIT SCHOKOLAD ROLADA BISZKOPTOWA O SMAKU CZEKOLADOWYM 290 G UKRAINA"
  },
  {
    "INDEKS": "58514",
    "NAZWA": "LOVARE MIESZANKA HERBAT Z DODATKAMI (2G X 24TOR) PASSION FRUIT UKRAINA",
    "RANKING": "346",
    "Grupa": "NAPOJE GORĄCE UKRAINA",
    "Producent": "LOVARE",
    "Kod Ean": "4820198876036",
    "x": "MIESZANKA HERBAT Z DODATKAMI (2G X 24TOR) PASSION FRUIT UKRAINA LOVARE"
  },
  {
    "INDEKS": "56221",
    "NAZWA": "LOVARE HERBATA PASSION FRUIT 80G UKRAINA",
    "RANKING": "351",
    "Grupa": "NAPOJE GORĄCE UKRAINA",
    "Producent": "LOVARE",
    "Kod Ean": "4820097818069",
    "x": "LOVARE HERBATA PASSION FRUIT 80G UKRAINA"
  },
  {
    "INDEKS": "56225",
    "NAZWA": "LOVARE HERBATA ROYAL DESSER 80G UKRAINA",
    "RANKING": "353",
    "Grupa": "NAPOJE GORĄCE UKRAINA",
    "Producent": "LOVARE",
    "Kod Ean": "4820097814610",
    "x": "LOVARE HERBATA ROYAL DESSER 80G UKRAINA"
  },
  {
    "INDEKS": "43069",
    "NAZWA": "KONTI DESER BONJOUR O SMAKU MANGO 232G UKRAINA",
    "RANKING": "354",
    "Grupa": "SŁODYCZE UKRAINA",
    "Producent": "KONTI",
    "Kod Ean": "4823088608205",
    "x": "KONTI DESER BONJOUR O SMAKU MANGO 232G UKRAINA"
  },
  {
    "INDEKS": "43074",
    "NAZWA": "KONTI CUKIERKI GOLDEN LILY PISTACJA 1KG UKRAINA",
    "RANKING": "355",
    "Grupa": "SŁODYCZE UKRAINA",
    "Producent": "KONTI",
    "Kod Ean": "4823088605563",
    "x": "KONTI CUKIERKI GOLDEN LILY PISTACJA 1KG UKRAINA"
  },
  {
    "INDEKS": "55760",
    "NAZWA": "GRONA ROKERSY KRAKERSY O SMAKU SERA CHEDDAR 400G UKRAINA",
    "RANKING": "357",
    "Grupa": "PRZEKĄSKI UKRAINA",
    "Producent": "ROKERSY",
    "Kod Ean": "4820258642526",
    "x": "GRONA ROKERSY KRAKERSY O SMAKU SERA CHEDDAR 400G UKRAINA"
  },
  {
    "INDEKS": "",
    "NAZWA": "",
    "RANKING": "",
    "Grupa": "",
    "Producent": "",
    "Kod Ean": "",
    "x": "#N/A"
  }
]
